<XML><Demon><Inferi><params><Main_Hand_Gold_Percentage>70</Main_Hand_Gold_Percentage><Athletics_Mastery>1</Athletics_Mastery><Default_Vitality>1</Default_Vitality><Xp>50</Xp><Explore_Speed>2</Explore_Speed><Base_Dexterity>-1</Base_Dexterity><Sneak_Armor_Mod>-25</Sneak_Armor_Mod><Aoo_Damage_Mod>100</Aoo_Damage_Mod><Hero_Level>1</Hero_Level><Sight_Range_Expansion_Backward>200</Sight_Range_Expansion_Backward><Arcane_Resistance>10</Arcane_Resistance><Attr_Points_Per_Level>5</Attr_Points_Per_Level><Starting_Identity_Points>3</Starting_Identity_Points><Demonology_Mastery>1</Demonology_Mastery><Instant_Attack_Mod>100</Instant_Attack_Mod><Strength>2</Strength><Fortitude>5</Fortitude><Destruction_Mastery_Score>1</Destruction_Mastery_Score><Mastery_Points_Per_Level>5</Mastery_Points_Per_Level><Sneak_Attack_Mod>100</Sneak_Attack_Mod><Diagonal_Attack_Mod>100</Diagonal_Attack_Mod><Shadow_Resistance>25</Shadow_Resistance><Force_Push_Mod>100</Force_Push_Mod><Order_Chance_Mod>100</Order_Chance_Mod><Warp_Mastery>1</Warp_Mastery><Demonology_Mastery_Score>1</Demonology_Mastery_Score><Watch_Defense_Others_Mod>100</Watch_Defense_Others_Mod><Aoo_Defense_Mod>100</Aoo_Defense_Mod><Counter_Attack_Mod>100</Counter_Attack_Mod><Force_Mod_Source_Weight>100</Force_Mod_Source_Weight><Offhand_Damage_Mod>75</Offhand_Damage_Mod><Endurance>10</Endurance><Side_Attack_Mod>100</Side_Attack_Mod><Counter_Mod>100</Counter_Mod><Consumption>1</Consumption><Force_Damage_Mod>100</Force_Damage_Mod><Toughness_Retainment>25</Toughness_Retainment><Detection>10</Detection><Dexterity>-1</Dexterity><Sight_Range_Expansion_Sides>150</Sight_Range_Expansion_Sides><Long_Reach_Damage_Mod>100</Long_Reach_Damage_Mod><Base_Spellpower>2</Base_Spellpower><Upkeep_Mod>100</Upkeep_Mod><Spirit>3</Spirit><Integrity>100</Integrity><Gold_Per_Level>100</Gold_Per_Level><Engaged_Aoo_Damage_Mod>100</Engaged_Aoo_Damage_Mod><Cadence_Ap_Mod>25</Cadence_Ap_Mod><Close_Quarters_Attack_Mod>100</Close_Quarters_Attack_Mod><Diagonal_Damage_Mod>100</Diagonal_Damage_Mod><Identity_Points_Per_Level>50</Identity_Points_Per_Level><Damage_Mod>100</Damage_Mod><Level>1</Level><Defense_Mod>100</Defense_Mod><Watch_Defense_Mod>100</Watch_Defense_Mod><Axe_Mastery>1</Axe_Mastery><Wisdom>-1</Wisdom><Aoo_Tough_Penalty>-50</Aoo_Tough_Penalty><Watch_Ap_Penalty_Mod>100</Watch_Ap_Penalty_Mod><Instant_Defense_Mod>100</Instant_Defense_Mod><Travel_Speed>2</Travel_Speed><Offhand_Attack_Mod>50</Offhand_Attack_Mod><Divination_Max_Sd_Mod>100</Divination_Max_Sd_Mod><Armor_Mod>100</Armor_Mod><Attack_Mod>100</Attack_Mod><Throw_Damage_Mod>100</Throw_Damage_Mod><Default_Wisdom>-1</Default_Wisdom><Sneak_Damage_Mod>25</Sneak_Damage_Mod><Total_Xp>100</Total_Xp><Noise>50</Noise><Base_Wisdom>-1</Base_Wisdom><Blade_Mastery_Score>1</Blade_Mastery_Score><Perception>20</Perception><Poison_Resistance>25</Poison_Resistance><Cadence_Sta_Mod>35</Cadence_Sta_Mod><Counter_Defense_Mod>100</Counter_Defense_Mod><Engaged_Aoo_Attack_Mod>100</Engaged_Aoo_Attack_Mod><Aoo_Attack_Mod>100</Aoo_Attack_Mod><Toughness_Recovery>25</Toughness_Recovery><Axe_Mastery_Score>1</Axe_Mastery_Score><Xp_Gain_Mod>100</Xp_Gain_Mod><Sight_Range_Expansion>200</Sight_Range_Expansion><Gold_Mod>100</Gold_Mod><Base_Vitality>1</Base_Vitality><Carrying_Capacity>25</Carrying_Capacity><Spellcraft_Mastery>1</Spellcraft_Mastery><Spellpower>2</Spellpower><Default_Dexterity>-1</Default_Dexterity><Power>10</Power><Destruction_Mastery>1</Destruction_Mastery><Initiative>4</Initiative><Stamina>5</Stamina><Watch_Attack_Others_Mod>100</Watch_Attack_Others_Mod><Interrupt_Damage>100</Interrupt_Damage><Armor_Gold_Percentage>40</Armor_Gold_Percentage><Fire_Resistance>35</Fire_Resistance><Xp_Level_Mod>100</Xp_Level_Mod><Divination_Pool_Mod>100</Divination_Pool_Mod><Force_Mod>100</Force_Mod><Long_Reach_Attack_Mod>100</Long_Reach_Attack_Mod><Ranged_Penalty_Mod>100</Ranged_Penalty_Mod><Self_Buff_Mod>60</Self_Buff_Mod><Watched_Attack_Mod>100</Watched_Attack_Mod><Summoned_Xp_Mod>100</Summoned_Xp_Mod><Counter_Tough_Penalty>-50</Counter_Tough_Penalty><Sneak_Defense_Mod>-50</Sneak_Defense_Mod><Blade_Mastery>1</Blade_Mastery><Instant_Tough_Penalty>-50</Instant_Tough_Penalty><Free_Masteries>7</Free_Masteries><Gold>25</Gold><Toughness_Death_Barrier_Mod>100</Toughness_Death_Barrier_Mod><Chaos_Resistance>35</Chaos_Resistance><Force_Knock_Mod>100</Force_Knock_Mod><Instant_Damage_Mod>100</Instant_Damage_Mod><Vitality>1</Vitality><Base_Strength>2</Base_Strength><Spell_Armor>5</Spell_Armor><Extra_Attacks_Point_Cost_Mod>50</Extra_Attacks_Point_Cost_Mod><Athletics_Mastery_Score>1</Athletics_Mastery_Score><Close_Quarters_Damage_Mod>100</Close_Quarters_Damage_Mod><Sneak_Protection>100</Sneak_Protection><Force_Spell_Damage_Mod>100</Force_Spell_Damage_Mod><Focus>100</Focus><Mastery_Points>-2</Mastery_Points><Watch_Attack_Mod>100</Watch_Attack_Mod><Height>200</Height><Default_Strength>2</Default_Strength><Warp_Mastery_Score>1</Warp_Mastery_Score><Toughness>5</Toughness><Throw_Attack_Mod>100</Throw_Attack_Mod><Default_Spellpower>2</Default_Spellpower><Engaged_Aoo_Defense_Mod>100</Engaged_Aoo_Defense_Mod><Side_Damage_Mod>100</Side_Damage_Mod><Memory_Remaining>4</Memory_Remaining><Spellcraft_Mastery_Score>1</Spellcraft_Mastery_Score><Memorization_Cap>4</Memorization_Cap><Girth>200</Girth></params><props><Race>Demon</Race><Group>Background</Group><Displayed_Name>Inferi</Displayed_Name><Offhand_Natural_Weapon>Average Horns</Offhand_Natural_Weapon><Id>160</Id><Principles></Principles><Natural_Weapon>Average Fist</Natural_Weapon><Aspect>Chaos</Aspect><Classifications>Humanoid;Hero;Demon;</Classifications><Type>chars</Type><Background>Inferi</Background><Deity>Annihilator;Consumer of Worlds;Warmaster;Underking;Sun God;</Deity><Soundset>Demon</Soundset><Image>mini/char td/demon/guard/Annihilator.jpg</Image><Name>Inferi</Name><Unique_Id>chars Inferi3016007315486608002</Unique_Id></props></Inferi><Inferi_Chaosborn><params><Main_Hand_Gold_Percentage>70</Main_Hand_Gold_Percentage><Athletics_Mastery>2</Athletics_Mastery><Default_Vitality>1</Default_Vitality><Xp>25</Xp><Explore_Speed>2</Explore_Speed><Sneak_Armor_Mod>-25</Sneak_Armor_Mod><Aoo_Damage_Mod>100</Aoo_Damage_Mod><Hero_Level>1</Hero_Level><Sight_Range_Expansion_Backward>200</Sight_Range_Expansion_Backward><Arcane_Resistance>20</Arcane_Resistance><Starting_Identity_Points>3</Starting_Identity_Points><Instant_Attack_Mod>100</Instant_Attack_Mod><Toughness_Death_Barrier_Mod>100</Toughness_Death_Barrier_Mod><Strength>2</Strength><Fortitude>5</Fortitude><Destruction_Mastery_Score>2</Destruction_Mastery_Score><Tactics_Mastery_Score>1</Tactics_Mastery_Score><Mastery_Points_Per_Level>5</Mastery_Points_Per_Level><Sneak_Attack_Mod>100</Sneak_Attack_Mod><Diagonal_Attack_Mod>100</Diagonal_Attack_Mod><Shadow_Resistance>25</Shadow_Resistance><Order_Chance_Mod>100</Order_Chance_Mod><Base_Willpower>1</Base_Willpower><Watch_Defense_Others_Mod>100</Watch_Defense_Others_Mod><Spirit>3</Spirit><Aoo_Defense_Mod>100</Aoo_Defense_Mod><Counter_Attack_Mod>100</Counter_Attack_Mod><Force_Mod_Source_Weight>100</Force_Mod_Source_Weight><Offhand_Damage_Mod>75</Offhand_Damage_Mod><Endurance>10</Endurance><Side_Attack_Mod>100</Side_Attack_Mod><Counter_Mod>100</Counter_Mod><Consumption>1</Consumption><Force_Damage_Mod>100</Force_Damage_Mod><War_Identity>2</War_Identity><Toughness_Retainment>25</Toughness_Retainment><Detection>10</Detection><Dexterity>-1</Dexterity><Sight_Range_Expansion_Sides>150</Sight_Range_Expansion_Sides><Two_Handed_Mastery>2</Two_Handed_Mastery><Long_Reach_Damage_Mod>100</Long_Reach_Damage_Mod><Base_Spellpower>2</Base_Spellpower><Upkeep_Mod>100</Upkeep_Mod><Freedom_Identity>1</Freedom_Identity><Integrity>100</Integrity><Gold_Per_Level>100</Gold_Per_Level><Engaged_Aoo_Damage_Mod>100</Engaged_Aoo_Damage_Mod><Close_Quarters_Attack_Mod>100</Close_Quarters_Attack_Mod><Diagonal_Damage_Mod>100</Diagonal_Damage_Mod><Blade_Mastery>3</Blade_Mastery><Identity_Points_Per_Level>50</Identity_Points_Per_Level><Damage_Mod>100</Damage_Mod><Level>1</Level><Base_Dexterity>-1</Base_Dexterity><Defense_Mod>100</Defense_Mod><Watch_Defense_Mod>100</Watch_Defense_Mod><Axe_Mastery>2</Axe_Mastery><Wisdom>-1</Wisdom><Aoo_Tough_Penalty>-50</Aoo_Tough_Penalty><Watch_Ap_Penalty_Mod>100</Watch_Ap_Penalty_Mod><Instant_Defense_Mod>100</Instant_Defense_Mod><Base_Wisdom>-1</Base_Wisdom><Travel_Speed>2</Travel_Speed><Offhand_Attack_Mod>50</Offhand_Attack_Mod><Divination_Max_Sd_Mod>100</Divination_Max_Sd_Mod><Tactics_Mastery>1</Tactics_Mastery><Mastery_Points>-2</Mastery_Points><Armor_Mod>100</Armor_Mod><Default_Willpower>1</Default_Willpower><Attack_Mod>100</Attack_Mod><Throw_Damage_Mod>100</Throw_Damage_Mod><Default_Wisdom>-1</Default_Wisdom><Sneak_Damage_Mod>25</Sneak_Damage_Mod><Total_Xp>100</Total_Xp><Noise>50</Noise><Blade_Mastery_Score>3</Blade_Mastery_Score><Leadership_Mastery>1</Leadership_Mastery><Perception>20</Perception><Poison_Resistance>25</Poison_Resistance><Counter_Defense_Mod>100</Counter_Defense_Mod><Engaged_Aoo_Attack_Mod>100</Engaged_Aoo_Attack_Mod><Aoo_Attack_Mod>100</Aoo_Attack_Mod><Toughness_Recovery>25</Toughness_Recovery><Axe_Mastery_Score>2</Axe_Mastery_Score><Spellpower>2</Spellpower><Sight_Range_Expansion>200</Sight_Range_Expansion><Cadence_Ap_Mod>25</Cadence_Ap_Mod><Blood_Magic_Mastery_Score>1</Blood_Magic_Mastery_Score><Law_Identity>-1</Law_Identity><Counter_Tough_Penalty>-50</Counter_Tough_Penalty><Base_Vitality>1</Base_Vitality><Carrying_Capacity>25</Carrying_Capacity><Extra_Attacks_Point_Cost_Mod>50</Extra_Attacks_Point_Cost_Mod><Cadence_Sta_Mod>35</Cadence_Sta_Mod><Default_Dexterity>-1</Default_Dexterity><Power>10</Power><Destruction_Mastery>2</Destruction_Mastery><Initiative>4</Initiative><Watch_Attack_Others_Mod>100</Watch_Attack_Others_Mod><Interrupt_Damage>100</Interrupt_Damage><Armor_Gold_Percentage>40</Armor_Gold_Percentage><Fire_Resistance>35</Fire_Resistance><Xp_Level_Mod>100</Xp_Level_Mod><Blunt_Mastery>2</Blunt_Mastery><Divination_Pool_Mod>100</Divination_Pool_Mod><Force_Mod>100</Force_Mod><Dual_Wielding_Mastery_Score>2</Dual_Wielding_Mastery_Score><Dual_Wielding_Mastery>2</Dual_Wielding_Mastery><Long_Reach_Attack_Mod>100</Long_Reach_Attack_Mod><Ranged_Penalty_Mod>100</Ranged_Penalty_Mod><Self_Buff_Mod>60</Self_Buff_Mod><Honor_Identity>2</Honor_Identity><Watched_Attack_Mod>100</Watched_Attack_Mod><Summoned_Xp_Mod>100</Summoned_Xp_Mod><Sneak_Defense_Mod>-50</Sneak_Defense_Mod><Instant_Tough_Penalty>-50</Instant_Tough_Penalty><Leadership_Mastery_Score>1</Leadership_Mastery_Score><Free_Masteries>7</Free_Masteries><Redemption_Mastery_Score>1</Redemption_Mastery_Score><Force_Push_Mod>100</Force_Push_Mod><Gold>-25</Gold><Attr_Points_Per_Level>5</Attr_Points_Per_Level><Chaos_Resistance>35</Chaos_Resistance><Force_Knock_Mod>100</Force_Knock_Mod><Blood_Magic_Mastery>1</Blood_Magic_Mastery><Instant_Damage_Mod>100</Instant_Damage_Mod><Vitality>1</Vitality><Base_Strength>2</Base_Strength><Spell_Armor>5</Spell_Armor><Gold_Mod>100</Gold_Mod><Athletics_Mastery_Score>2</Athletics_Mastery_Score><Close_Quarters_Damage_Mod>100</Close_Quarters_Damage_Mod><Stamina>5</Stamina><Sneak_Protection>100</Sneak_Protection><Force_Spell_Damage_Mod>100</Force_Spell_Damage_Mod><Two_Handed_Mastery_Score>2</Two_Handed_Mastery_Score><Focus>100</Focus><Watch_Attack_Mod>100</Watch_Attack_Mod><Redemption_Mastery>1</Redemption_Mastery><Height>200</Height><Default_Strength>2</Default_Strength><Treachery_Identity>-2</Treachery_Identity><Toughness>5</Toughness><Throw_Attack_Mod>100</Throw_Attack_Mod><Default_Spellpower>2</Default_Spellpower><Peace_Identity>-2</Peace_Identity><Engaged_Aoo_Defense_Mod>100</Engaged_Aoo_Defense_Mod><Side_Damage_Mod>100</Side_Damage_Mod><Memory_Remaining>4</Memory_Remaining><Memorization_Cap>4</Memorization_Cap><Blunt_Mastery_Score>2</Blunt_Mastery_Score><Xp_Gain_Mod>100</Xp_Gain_Mod><Willpower>1</Willpower><Girth>200</Girth></params><props><Race>Demon</Race><Group>Background</Group><Displayed_Name>Inferi Chaosborn</Displayed_Name><Offhand_Natural_Weapon>Average Fist</Offhand_Natural_Weapon><Id>162</Id><Principles>War(2);Peace(-2);Honor(2);Treachery(-2);Freedom(1);Law(-1);</Principles><Natural_Weapon>Average Fist</Natural_Weapon><Aspect>Chaos</Aspect><Classifications>Humanoid;Hero;Demon;</Classifications><Type>chars</Type><Background>Inferi Hellguard</Background><Deity>Annihilator;Consumer of Worlds;Warmaster;Underking;Sun God;</Deity><Version>0.05</Version><Soundset>Demon</Soundset><Image>mini/char td/demon/guard/knight2.jpg</Image><Name>Inferi Chaosborn</Name><Unique_Id>chars Inferi Chaosborn2793666886524385112</Unique_Id></props></Inferi_Chaosborn><Inferi_Warpborn><params><Main_Hand_Gold_Percentage>70</Main_Hand_Gold_Percentage><Default_Charisma>4</Default_Charisma><Xp>50</Xp><Explore_Speed>2</Explore_Speed><Sneak_Armor_Mod>-25</Sneak_Armor_Mod><Default_Agility>-1</Default_Agility><Aoo_Damage_Mod>100</Aoo_Damage_Mod><Charisma>4</Charisma><Hero_Level>1</Hero_Level><Sight_Range_Expansion_Backward>200</Sight_Range_Expansion_Backward><Arcane_Resistance>20</Arcane_Resistance><Attr_Points_Per_Level>5</Attr_Points_Per_Level><Starting_Identity_Points>3</Starting_Identity_Points><Charity_Identity>-1</Charity_Identity><Demonology_Mastery>2</Demonology_Mastery><Instant_Attack_Mod>100</Instant_Attack_Mod><Strength>-1</Strength><Fortitude>5</Fortitude><Mastery_Points_Per_Level>5</Mastery_Points_Per_Level><Base_Intelligence>1</Base_Intelligence><Sneak_Attack_Mod>100</Sneak_Attack_Mod><Diagonal_Attack_Mod>100</Diagonal_Attack_Mod><Weight>-15</Weight><Force_Push_Mod>100</Force_Push_Mod><Order_Chance_Mod>100</Order_Chance_Mod><Warp_Mastery>4</Warp_Mastery><Demonology_Mastery_Score>2</Demonology_Mastery_Score><Knowledge>1</Knowledge><Watch_Defense_Others_Mod>100</Watch_Defense_Others_Mod><Aoo_Defense_Mod>100</Aoo_Defense_Mod><Counter_Attack_Mod>100</Counter_Attack_Mod><Force_Mod_Source_Weight>100</Force_Mod_Source_Weight><Offhand_Damage_Mod>75</Offhand_Damage_Mod><Endurance>10</Endurance><Side_Attack_Mod>100</Side_Attack_Mod><Counter_Mod>100</Counter_Mod><Consumption>1</Consumption><Toughness_Retainment>25</Toughness_Retainment><Sight_Range_Expansion_Sides>150</Sight_Range_Expansion_Sides><Ambition_Identity>1</Ambition_Identity><Enchantment_Mastery_Score>2</Enchantment_Mastery_Score><Long_Reach_Damage_Mod>100</Long_Reach_Damage_Mod><Base_Spellpower>3</Base_Spellpower><Upkeep_Mod>100</Upkeep_Mod><Freedom_Identity>2</Freedom_Identity><Spirit>3</Spirit><Integrity>100</Integrity><Gold_Per_Level>100</Gold_Per_Level><Engaged_Aoo_Damage_Mod>100</Engaged_Aoo_Damage_Mod><Close_Quarters_Attack_Mod>100</Close_Quarters_Attack_Mod><Diagonal_Damage_Mod>100</Diagonal_Damage_Mod><Identity_Points_Per_Level>50</Identity_Points_Per_Level><Damage_Mod>100</Damage_Mod><Level>1</Level><Defense_Mod>100</Defense_Mod><Watch_Defense_Mod>100</Watch_Defense_Mod><Default_Intelligence>1</Default_Intelligence><Aoo_Tough_Penalty>-50</Aoo_Tough_Penalty><Base_Knowledge>1</Base_Knowledge><Watch_Ap_Penalty_Mod>100</Watch_Ap_Penalty_Mod><Instant_Defense_Mod>100</Instant_Defense_Mod><Travel_Speed>2</Travel_Speed><Force_Mod>100</Force_Mod><Divination_Max_Sd_Mod>100</Divination_Max_Sd_Mod><Armor_Mod>100</Armor_Mod><Attack_Mod>100</Attack_Mod><Throw_Damage_Mod>100</Throw_Damage_Mod><Sneak_Damage_Mod>25</Sneak_Damage_Mod><Total_Xp>100</Total_Xp><Noise>50</Noise><Base_Agility>-1</Base_Agility><Perception>20</Perception><Poison_Resistance>25</Poison_Resistance><Counter_Defense_Mod>100</Counter_Defense_Mod><Enchantment_Mastery>2</Enchantment_Mastery><Engaged_Aoo_Attack_Mod>100</Engaged_Aoo_Attack_Mod><Aoo_Attack_Mod>100</Aoo_Attack_Mod><Toughness_Recovery>25</Toughness_Recovery><Psychic_Mastery>1</Psychic_Mastery><Spellpower>3</Spellpower><Default_Knowledge>1</Default_Knowledge><Attr_Points>-2</Attr_Points><Sight_Range_Expansion>200</Sight_Range_Expansion><Cadence_Ap_Mod>25</Cadence_Ap_Mod><Law_Identity>-2</Law_Identity><Counter_Tough_Penalty>-50</Counter_Tough_Penalty><Carrying_Capacity>25</Carrying_Capacity><Spellcraft_Mastery>3</Spellcraft_Mastery><Extra_Attacks_Point_Cost_Mod>50</Extra_Attacks_Point_Cost_Mod><Psychic_Mastery_Score>1</Psychic_Mastery_Score><Cadence_Sta_Mod>35</Cadence_Sta_Mod><Offhand_Attack_Mod>50</Offhand_Attack_Mod><Power>10</Power><Initiative>4</Initiative><Agility>-1</Agility><Intelligence>1</Intelligence><Base_Charisma>4</Base_Charisma><Watch_Attack_Others_Mod>100</Watch_Attack_Others_Mod><Interrupt_Damage>100</Interrupt_Damage><Armor_Gold_Percentage>40</Armor_Gold_Percentage><Fire_Resistance>35</Fire_Resistance><Divination_Pool_Mod>100</Divination_Pool_Mod><Long_Reach_Attack_Mod>100</Long_Reach_Attack_Mod><Ranged_Penalty_Mod>100</Ranged_Penalty_Mod><Self_Buff_Mod>60</Self_Buff_Mod><Honor_Identity>-2</Honor_Identity><Watched_Attack_Mod>100</Watched_Attack_Mod><Summoned_Xp_Mod>100</Summoned_Xp_Mod><Sneak_Defense_Mod>-50</Sneak_Defense_Mod><Shadow_Resistance>25</Shadow_Resistance><Instant_Tough_Penalty>-50</Instant_Tough_Penalty><Detection>10</Detection><Free_Masteries>4</Free_Masteries><Gold>-25</Gold><Toughness_Death_Barrier_Mod>100</Toughness_Death_Barrier_Mod><Chaos_Resistance>35</Chaos_Resistance><Force_Knock_Mod>100</Force_Knock_Mod><Instant_Damage_Mod>100</Instant_Damage_Mod><Base_Strength>-1</Base_Strength><Spell_Armor>5</Spell_Armor><Force_Damage_Mod>100</Force_Damage_Mod><Gold_Mod>100</Gold_Mod><Close_Quarters_Damage_Mod>100</Close_Quarters_Damage_Mod><Stamina>5</Stamina><Sneak_Protection>100</Sneak_Protection><Force_Spell_Damage_Mod>100</Force_Spell_Damage_Mod><Focus>100</Focus><Watch_Attack_Mod>100</Watch_Attack_Mod><Height>200</Height><Default_Strength>-1</Default_Strength><Treachery_Identity>2</Treachery_Identity><Warp_Mastery_Score>4</Warp_Mastery_Score><Toughness>5</Toughness><Throw_Attack_Mod>100</Throw_Attack_Mod><Default_Spellpower>3</Default_Spellpower><Engaged_Aoo_Defense_Mod>100</Engaged_Aoo_Defense_Mod><Side_Damage_Mod>100</Side_Damage_Mod><Memory_Remaining>4</Memory_Remaining><Spellcraft_Mastery_Score>3</Spellcraft_Mastery_Score><Memorization_Cap>4</Memorization_Cap><Xp_Gain_Mod>100</Xp_Gain_Mod><Xp_Level_Mod>100</Xp_Level_Mod><Girth>200</Girth></params><props><Race>Demon</Race><Group>Background</Group><Displayed_Name>Inferi Warpborn</Displayed_Name><Offhand_Natural_Weapon>Average Fist</Offhand_Natural_Weapon><Id>163</Id><Principles>Treachery(2);Honor(-2);Freedom(2);Law(-2);Ambition(1);Charity(-1);</Principles><Natural_Weapon>Average Fist</Natural_Weapon><Aspect>Chaos</Aspect><Classifications>Humanoid;Hero;Demon;</Classifications><Type>chars</Type><Background>Inferi Succubus</Background><Deity><![CDATA[Queen of Lust;Consumer of Worlds;World Serpent;Crimson Queen;Night Lord;Witch King;Arachnia ]]></Deity><Version>0.05</Version><Soundset>Female</Soundset><Image>mini/char td/demon/temptress.jpg</Image><Name>Inferi Warpborn</Name><Unique_Id>chars Inferi Warpborn1529966922745280663</Unique_Id></props></Inferi_Warpborn><Inferi_Demonborn><params><Main_Hand_Gold_Percentage>70</Main_Hand_Gold_Percentage><Athletics_Mastery>2</Athletics_Mastery><Default_Vitality>3</Default_Vitality><Xp>25</Xp><Explore_Speed>2</Explore_Speed><Base_Dexterity>-1</Base_Dexterity><Sneak_Armor_Mod>-25</Sneak_Armor_Mod><Aoo_Damage_Mod>100</Aoo_Damage_Mod><Hero_Level>1</Hero_Level><Sight_Range_Expansion_Backward>200</Sight_Range_Expansion_Backward><Affliction_Mastery>1</Affliction_Mastery><Starting_Identity_Points>3</Starting_Identity_Points><Charity_Identity>-2</Charity_Identity><Demonology_Mastery>4</Demonology_Mastery><Instant_Attack_Mod>100</Instant_Attack_Mod><Default_Agility>-1</Default_Agility><Strength>3</Strength><Fortitude>5</Fortitude><Destruction_Mastery_Score>1</Destruction_Mastery_Score><Mastery_Points_Per_Level>5</Mastery_Points_Per_Level><Base_Intelligence>-1</Base_Intelligence><Blunt_Mastery>3</Blunt_Mastery><Sneak_Attack_Mod>100</Sneak_Attack_Mod><Diagonal_Attack_Mod>100</Diagonal_Attack_Mod><Weight>25</Weight><Force_Push_Mod>100</Force_Push_Mod><Order_Chance_Mod>100</Order_Chance_Mod><Demonology_Mastery_Score>4</Demonology_Mastery_Score><Watch_Defense_Others_Mod>100</Watch_Defense_Others_Mod><Aoo_Defense_Mod>100</Aoo_Defense_Mod><Counter_Attack_Mod>100</Counter_Attack_Mod><Force_Mod_Source_Weight>100</Force_Mod_Source_Weight><Offhand_Damage_Mod>75</Offhand_Damage_Mod><Endurance>10</Endurance><Side_Attack_Mod>100</Side_Attack_Mod><Counter_Mod>100</Counter_Mod><Consumption>1</Consumption><War_Identity>2</War_Identity><Toughness_Retainment>25</Toughness_Retainment><Dexterity>-1</Dexterity><Sight_Range_Expansion_Sides>150</Sight_Range_Expansion_Sides><Two_Handed_Mastery>2</Two_Handed_Mastery><Long_Reach_Damage_Mod>100</Long_Reach_Damage_Mod><Base_Spellpower>2</Base_Spellpower><Upkeep_Mod>100</Upkeep_Mod><Spirit>3</Spirit><Integrity>100</Integrity><Gold_Per_Level>100</Gold_Per_Level><Attr_Points_Per_Level>5</Attr_Points_Per_Level><Engaged_Aoo_Damage_Mod>100</Engaged_Aoo_Damage_Mod><Cadence_Ap_Mod>25</Cadence_Ap_Mod><Close_Quarters_Attack_Mod>100</Close_Quarters_Attack_Mod><Diagonal_Damage_Mod>100</Diagonal_Damage_Mod><Identity_Points_Per_Level>50</Identity_Points_Per_Level><Damage_Mod>100</Damage_Mod><Level>1</Level><Defense_Mod>100</Defense_Mod><Watch_Defense_Mod>100</Watch_Defense_Mod><Default_Intelligence>-1</Default_Intelligence><Axe_Mastery>3</Axe_Mastery><Wisdom>-1</Wisdom><Aoo_Tough_Penalty>-50</Aoo_Tough_Penalty><Watch_Ap_Penalty_Mod>100</Watch_Ap_Penalty_Mod><Instant_Defense_Mod>100</Instant_Defense_Mod><Affliction_Mastery_Score>1</Affliction_Mastery_Score><Travel_Speed>2</Travel_Speed><Force_Mod>100</Force_Mod><Divination_Max_Sd_Mod>100</Divination_Max_Sd_Mod><Mastery_Points>-2</Mastery_Points><Armor_Mod>100</Armor_Mod><Attack_Mod>100</Attack_Mod><Throw_Damage_Mod>100</Throw_Damage_Mod><Default_Wisdom>-1</Default_Wisdom><Sneak_Damage_Mod>25</Sneak_Damage_Mod><Total_Xp>100</Total_Xp><Noise>50</Noise><Base_Wisdom>-1</Base_Wisdom><Base_Agility>-1</Base_Agility><Perception>20</Perception><Poison_Resistance>25</Poison_Resistance><Counter_Defense_Mod>100</Counter_Defense_Mod><Engaged_Aoo_Attack_Mod>100</Engaged_Aoo_Attack_Mod><Aoo_Attack_Mod>100</Aoo_Attack_Mod><Toughness_Recovery>25</Toughness_Recovery><Axe_Mastery_Score>3</Axe_Mastery_Score><Spellpower>2</Spellpower><Sight_Range_Expansion>200</Sight_Range_Expansion><Gold_Mod>100</Gold_Mod><Base_Strength>3</Base_Strength><Counter_Tough_Penalty>-50</Counter_Tough_Penalty><Base_Vitality>3</Base_Vitality><Carrying_Capacity>25</Carrying_Capacity><Cadence_Sta_Mod>35</Cadence_Sta_Mod><Default_Dexterity>-1</Default_Dexterity><Offhand_Attack_Mod>50</Offhand_Attack_Mod><Power>10</Power><Destruction_Mastery>1</Destruction_Mastery><Initiative>4</Initiative><Stamina>5</Stamina><Agility>-1</Agility><Intelligence>-1</Intelligence><Watch_Attack_Others_Mod>100</Watch_Attack_Others_Mod><Interrupt_Damage>100</Interrupt_Damage><Armor_Gold_Percentage>40</Armor_Gold_Percentage><Fire_Resistance>35</Fire_Resistance><Divination_Pool_Mod>100</Divination_Pool_Mod><Long_Reach_Attack_Mod>100</Long_Reach_Attack_Mod><Ranged_Penalty_Mod>100</Ranged_Penalty_Mod><Self_Buff_Mod>60</Self_Buff_Mod><Watched_Attack_Mod>100</Watched_Attack_Mod><Summoned_Xp_Mod>100</Summoned_Xp_Mod><Sneak_Defense_Mod>-50</Sneak_Defense_Mod><Shadow_Resistance>35</Shadow_Resistance><Instant_Tough_Penalty>-50</Instant_Tough_Penalty><Warcry_Mastery>3</Warcry_Mastery><Detection>10</Detection><Free_Masteries>6</Free_Masteries><Two_Handed_Mastery_Score>2</Two_Handed_Mastery_Score><Gold>-25</Gold><Toughness_Death_Barrier_Mod>100</Toughness_Death_Barrier_Mod><Chaos_Resistance>35</Chaos_Resistance><Force_Knock_Mod>100</Force_Knock_Mod><Instant_Damage_Mod>100</Instant_Damage_Mod><Vitality>3</Vitality><Sneak_Protection>100</Sneak_Protection><Spell_Armor>5</Spell_Armor><Force_Damage_Mod>100</Force_Damage_Mod><Extra_Attacks_Point_Cost_Mod>50</Extra_Attacks_Point_Cost_Mod><Athletics_Mastery_Score>2</Athletics_Mastery_Score><Close_Quarters_Damage_Mod>100</Close_Quarters_Damage_Mod><Honor_Identity>-1</Honor_Identity><Ambition_Identity>2</Ambition_Identity><Force_Spell_Damage_Mod>100</Force_Spell_Damage_Mod><Warcry_Mastery_Score>3</Warcry_Mastery_Score><Focus>100</Focus><Watch_Attack_Mod>100</Watch_Attack_Mod><Height>200</Height><Default_Strength>3</Default_Strength><Treachery_Identity>1</Treachery_Identity><Toughness>5</Toughness><Throw_Attack_Mod>100</Throw_Attack_Mod><Default_Spellpower>2</Default_Spellpower><Peace_Identity>-2</Peace_Identity><Engaged_Aoo_Defense_Mod>100</Engaged_Aoo_Defense_Mod><Side_Damage_Mod>100</Side_Damage_Mod><Memory_Remaining>4</Memory_Remaining><Memorization_Cap>4</Memorization_Cap><Blunt_Mastery_Score>3</Blunt_Mastery_Score><Xp_Level_Mod>100</Xp_Level_Mod><Xp_Gain_Mod>100</Xp_Gain_Mod><Girth>200</Girth></params><props><Race>Demon</Race><Group>Background</Group><Displayed_Name>Inferi Demonborn</Displayed_Name><Offhand_Natural_Weapon>Average Horns</Offhand_Natural_Weapon><Id>164</Id><Principles>War(2);Peace(-2);Ambition(2);Charity(-2);Treachery(1);Honor(-1);</Principles><Natural_Weapon>Average Claws</Natural_Weapon><Aspect>Chaos</Aspect><Classifications>Humanoid;Hero;Demon;</Classifications><Type>chars</Type><Background>Inferi Hellspawn</Background><Deity><![CDATA[Consumer of Worlds;Death Gorger;Lord of Decay;Annihilator;Underking;Witch King;Queen of Lust;Warmaster; ]]></Deity><Version>0.05</Version><Soundset>Demon</Soundset><Image>mini/char td/demon pawn/Fire Daemon.jpg</Image><Name>Inferi Demonborn</Name><Unique_Id>chars Inferi Demonborn-4474321296970784441</Unique_Id></props></Inferi_Demonborn></Demon></XML>