<XML><Elf><Gwynn_UNICODE45CODEEND_1_UNICODE45CODEEND_1_UNICODE45CODEEND_1><params><Base_Strength>17.0</Base_Strength><Divination_Max_Sd_Mod>100</Divination_Max_Sd_Mod><Dual_Wielding_Mastery>15.0</Dual_Wielding_Mastery><N_Of_Actions_Percentage>1000000</N_Of_Actions_Percentage><Xp_Gain_Mod>100</Xp_Gain_Mod><Watch_Attack_Others_Mod>100</Watch_Attack_Others_Mod><Gold>4057</Gold><Spirit>4</Spirit><Diagonal_Attack_Mod>100</Diagonal_Attack_Mod><Shadow_Mastery_Score>13</Shadow_Mastery_Score><Vigor>100</Vigor><Engaged_Aoo_Defense_Mod>100</Engaged_Aoo_Defense_Mod><Strength>17</Strength><Toughness_Percentage>100</Toughness_Percentage><Base_Spellpower>9</Base_Spellpower><Fortitude>5</Fortitude><Charisma>4</Charisma><Default_Strength>-1</Default_Strength><Defense_Mod>100</Defense_Mod><Watch_Ap_Penalty_Mod>100</Watch_Ap_Penalty_Mod><Instant_Stamina_Penalty>-50</Instant_Stamina_Penalty><Instant_Attack_Mod>100</Instant_Attack_Mod><Sight_Range_Expansion>200</Sight_Range_Expansion><Diagonal_Damage_Mod>100</Diagonal_Damage_Mod><Watch_Defense_Mod>100</Watch_Defense_Mod><Illumination>256.0</Illumination><Endurance>30</Endurance><Instant_Damage_Mod>100</Instant_Damage_Mod><Cadence_Sta_Mod>-25</Cadence_Sta_Mod><Resistance>15</Resistance><Defense_Mastery>5.0</Defense_Mastery><Sight_Range>3</Sight_Range><Attr_Points_Per_Level>13.0</Attr_Points_Per_Level><Watch_Defense_Others_Mod>100</Watch_Defense_Others_Mod><Damage_Mod>100</Damage_Mod><Summoned_Xp_Mod>100</Summoned_Xp_Mod><Engaged_Aoo_Attack_Mod>100</Engaged_Aoo_Attack_Mod><Default_Vitality>-1</Default_Vitality><Motivation>50</Motivation><Main_Hand_Gold_Percentage>70</Main_Hand_Gold_Percentage><Witchery_Mastery>15.0</Witchery_Mastery><Power>277</Power><Force_Knock_Mod>100</Force_Knock_Mod><Endurance_Percentage>100</Endurance_Percentage><Counter_Attack_Mod>100</Counter_Attack_Mod><Default_Dexterity>1</Default_Dexterity><Level>10.0</Level><Counter_Mod>100</Counter_Mod><Mobility_Mastery>20.0</Mobility_Mastery><Order_Chance_Mod>100</Order_Chance_Mod><Quick_Slots>2</Quick_Slots><Knowledge>7</Knowledge><Interrupt_Damage>100</Interrupt_Damage><C_N_Of_Counters>2</C_N_Of_Counters><Force_Spell_Damage_Mod>100</Force_Spell_Damage_Mod><Explore_Speed>2</Explore_Speed><Damage>10</Damage><Stealth>4</Stealth><Offhand_Attack_Mod>50</Offhand_Attack_Mod><Health>100</Health><Ranged_Penalty_Mod>100</Ranged_Penalty_Mod><Sight_Range_Expansion_Sides>150</Sight_Range_Expansion_Sides><Sneak_Attack_Mod>100</Sneak_Attack_Mod><Aoo_Defense_Mod>100</Aoo_Defense_Mod><Base_Intelligence>9</Base_Intelligence><Carrying_Capacity>50</Carrying_Capacity><Armor_Mod>100</Armor_Mod><Force_Mod_Source_Weight>100</Force_Mod_Source_Weight><Cadence_Ap_Mod>-25</Cadence_Ap_Mod><Divination_Pool_Mod>100</Divination_Pool_Mod><Toughness>15</Toughness><Defense>5</Defense><Force_Push_Mod>100</Force_Push_Mod><Gold_Mod>100</Gold_Mod><Armor_Gold_Percentage>40</Armor_Gold_Percentage><Base_Agility>17.0</Base_Agility><Watch_Attack_Mod>100</Watch_Attack_Mod><Force_Damage_Mod>100</Force_Damage_Mod><Throw_Attack_Mod>100</Throw_Attack_Mod><Default_Agility>1</Default_Agility><Aoo_Stamina_Penalty>-50</Aoo_Stamina_Penalty><Total_Xp>2779.0</Total_Xp><N_Of_Counters_Percentage>1000000</N_Of_Counters_Percentage><Xp_Level_Mod>100</Xp_Level_Mod><Essence_Percentage>100</Essence_Percentage><Dual_Wielding_Mastery_Score>15</Dual_Wielding_Mastery_Score><Hero_Level>8.0</Hero_Level><Base_Dexterity>14.0</Base_Dexterity><Girth>350</Girth><Holy_Resistance>15</Holy_Resistance><Force_Mod>100</Force_Mod><Long_Reach_Attack_Mod>100</Long_Reach_Attack_Mod><Attack_Mod>100</Attack_Mod><Dexterity>14</Dexterity><N_Of_Actions>4</N_Of_Actions><Upkeep_Mod>100</Upkeep_Mod><Sneak_Damage_Mod>25</Sneak_Damage_Mod><Travel_Speed>4</Travel_Speed><Blade_Mastery_Score>20</Blade_Mastery_Score><Consumption>1</Consumption><Counter_Stamina_Penalty>-50</Counter_Stamina_Penalty><Starting_Focus>25</Starting_Focus><Mobility_Mastery_Score>20</Mobility_Mastery_Score><Stealth_Mastery_Score>10</Stealth_Mastery_Score><N_Of_Counters>1</N_Of_Counters><Integrity>100</Integrity><Stamina_Percentage>100</Stamina_Percentage><Agility>17</Agility><Sight_Range_Expansion_Backward>200</Sight_Range_Expansion_Backward><Initiative_Modifier>10</Initiative_Modifier><Detection>8</Detection><Shadow_Mastery>13.0</Shadow_Mastery><Identity_Points_Per_Level>50</Identity_Points_Per_Level><Base_Willpower>12.0</Base_Willpower><Blade_Mastery>20.0</Blade_Mastery><Base_Vitality>11.0</Base_Vitality><Watched_Attack_Mod>100</Watched_Attack_Mod><Long_Reach_Damage_Mod>100</Long_Reach_Damage_Mod><Arcane_Resistance>15</Arcane_Resistance><Focus_Recover_Req>10</Focus_Recover_Req><Oneness>50</Oneness><Base_Wisdom>9.0</Base_Wisdom><Combat_Readiness>50</Combat_Readiness><Morale_Percentage>1000000</Morale_Percentage><Spellcraft_Mastery_Score>5</Spellcraft_Mastery_Score><Spellpower>9</Spellpower><Weight>125</Weight><Toughness_Death_Barrier_Mod>100</Toughness_Death_Barrier_Mod><Morale>30</Morale><Attack>5</Attack><Initiative_Percentage>100</Initiative_Percentage><Stealth_Mastery>10.0</Stealth_Mastery><Identity_Points>6</Identity_Points><Battle_Spirit>100</Battle_Spirit><Free_Masteries>4</Free_Masteries><Athletics_Mastery>10.0</Athletics_Mastery><Wisdom>9</Wisdom><Aoo_Damage_Mod>100</Aoo_Damage_Mod><Xp>383</Xp><Memory_Remaining>4</Memory_Remaining><Sneak_Protection>100</Sneak_Protection><Defense_Mastery_Score>5</Defense_Mastery_Score><Base_Charisma>4</Base_Charisma><Side_Attack_Mod>100</Side_Attack_Mod><Height>190</Height><Vitality>11</Vitality><Sneak_Defense_Mod>-50</Sneak_Defense_Mod><Base_Damage>3</Base_Damage><Base_Knowledge>7</Base_Knowledge><Extra_Attacks_Point_Cost_Mod>50</Extra_Attacks_Point_Cost_Mod><Athletics_Mastery_Score>10</Athletics_Mastery_Score><Initiative_Bonus>5</Initiative_Bonus><Shadow_Resistance>15</Shadow_Resistance><Witchery_Mastery_Score>15</Witchery_Mastery_Score><Focus>100</Focus><Stamina>10</Stamina><Toughness_Recovery>25</Toughness_Recovery><Sneak_Armor_Mod>-25</Sneak_Armor_Mod><Instant_Defense_Mod>100</Instant_Defense_Mod><Side_Damage_Mod>100</Side_Damage_Mod><Spellcraft_Mastery>5.0</Spellcraft_Mastery><Close_Quarters_Attack_Mod>100</Close_Quarters_Attack_Mod><Offhand_Damage_Mod>75</Offhand_Damage_Mod><Close_Quarters_Damage_Mod>100</Close_Quarters_Damage_Mod><Counter_Defense_Mod>100</Counter_Defense_Mod><Chaos_Resistance>15</Chaos_Resistance><Willpower>12</Willpower><Aoo_Attack_Mod>100</Aoo_Attack_Mod><C_Morale>30</C_Morale><C_Quick_Slots>4</C_Quick_Slots><C_Stamina>5</C_Stamina><Throw_Damage_Mod>100</Throw_Damage_Mod><Starting_Identity_Points>3</Starting_Identity_Points><Essence>25</Essence><Gold_Per_Level>100</Gold_Per_Level><Engaged_Aoo_Damage_Mod>100</Engaged_Aoo_Damage_Mod><Memorization_Cap>9</Memorization_Cap><Focus_Percentage>100</Focus_Percentage><Organization>100</Organization><Intelligence>9</Intelligence><Mastery_Points_Per_Level>21.0</Mastery_Points_Per_Level></params><props><Image>demo\heroes\gwyn 128.jpg</Image><Classes><![CDATA[Rogue;Trickster;Apostate;Rogue;Trickster;Acrobat;Thug;Acrobat;Thug;Death Dancer;Death Dancer;Death Dancer;]]></Classes><Quick_Items>Minor Stamina Potion;Minor Healing Potion;Minor Focus Potion</Quick_Items><Id>1049</Id><Displayed_Name>Gwynn</Displayed_Name><Emblem>UI/emblems/auto/free league.png</Emblem><Perks><![CDATA[Surreptitious;Accurate;Swift;Relentless;Tough II;Accurate II;Nimble II;Accurate III;Nimble III;]]></Perks><Type>chars</Type><Group>IGG</Group><Race>Elf</Race><Gender>MALE</Gender><Name>Gwynn - 1 - 1 - 1</Name><Main_Hand_Item>Dark Steel Scimitar</Main_Hand_Item><Version>0.9.0c</Version><Mastery_Ranks_2><![CDATA[Blade Mastery;Mobility Mastery;Witchery Mastery;Mobility Mastery;Blade Mastery;Dual Wielding Mastery;]]></Mastery_Ranks_2><Spellbook></Spellbook><Inventory><![CDATA[Green Luminescent Fungi (Consumable);Yellow Luminescent Fungi (Consumable);Purple Luminescent Fungi (Consumable);Steel Dagger;Food;Steel Knife]]></Inventory><Natural_Weapon>Petty Fist</Natural_Weapon><Rank>New Hero</Rank><Skills><![CDATA[Greater Dexterity;Short Sword Specialization;Greater Agility;Forbidden Knowledge;Mercurial;Short Sword Specialization;]]></Skills><Known_Spells><![CDATA[Drain Focus;Hallucinations;Malediction;Curse Weapon;Cripple;Enfeeble;Shadow Flame;Fear;Scare;Shadow Bolt;]]></Known_Spells><Armor_Item>Superior Tough Leather Rogue Outfit</Armor_Item><Unique_Id>chars Gwynbleid-4556633272379557649</Unique_Id><Aspect>Neutral</Aspect><Memorized_Spells><![CDATA[Shadow Bolt;Drain Stamina;Drain Focus;Cripple;Enfeeble;Scare;Hallucinations;Drain Life;]]></Memorized_Spells><Mastery_Ranks_1><![CDATA[Blade Mastery;Stealth Mastery;Mobility Mastery;Witchery Mastery;Shadow Mastery;Mobility Mastery;Blade Mastery;]]></Mastery_Ranks_1><Offhand_Natural_Weapon>Petty Fist</Offhand_Natural_Weapon><Second_Class>Trickster</Second_Class><Classifications>Humanoid;Hero</Classifications><Jewelry>Minor Bone Ring of Toughness(+15)</Jewelry><Off_Hand_Item>Moon Silver Kris</Off_Hand_Item><Background>Elf</Background><First_Class>Rogue</First_Class><Verbatim_Spells><![CDATA[Shadow Fury CAST black abyss;Shadow Fury CAST black centering;Shadow Fury CAST black centering gravity;Shadow Fury CAST black centering gravity 2;Shadow Fury CAST black cloud;Shadow Fury CAST black cloud 2;Shadow Fury CAST black font;Shadow Fury CAST black fountain;Shadow Fury CAST black gathering;Shadow Fury CAST black grasp 2;Shadow Fury CAST black grasp 3;Shadow Fury CAST black hole hypnotic attached;Shadow Fury CAST black hole hypnotic attached 2;Shadow Fury CAST black pillar;Shadow Fury CAST black pillar 2;Shadow Fury CAST black pillar 3;Shadow Fury CAST black pillar high;Shadow Fury CAST black pit;Shadow Fury CAST black pit 2;Shadow Fury CAST black pool;Shadow Fury CAST black ring;Shadow Fury CAST black swarm;Shadow Fury CAST black veil;Shadow Fury CAST black veil 2;Shadow Fury CAST black waterfall;Shadow Fury CAST black wormhole;Shadow Fury CAST smoke sphere;Shadow Fury CAST smoke sphere hypnotic;Shadow Fury CAST smoke sphere hypnotic attached;Shadow Fury CAST smoke sphere hypnotic large;Shadow Fury CAST smoke sphere hypnotic large 2;Shadow Fury CAST smoke sphere large;Shadow Fury CAST smoke sphere lean;Shadow Fury CAST volumetric fog black;Shadow Fury CAST volumetric fog black 2;Shadow Fury CAST volumetric fog black hypnotic;Shadow Fury CAST volumetric fog blackest;Shadow Fury CAST volumetric fog blackest web;Shadow Fury CAST black missile cone;Shadow Fury CAST black missile cone 2;Shadow Fury CAST black missile cone 3;]]></Verbatim_Spells><Workspace_Group>Test</Workspace_Group><Deity>Faithless</Deity><Principles>Freedom;War;</Principles><Unlocked_Masteries>Athletics Mastery;Defense Mastery;Spellcraft Mastery;</Unlocked_Masteries></props></Gwynn_UNICODE45CODEEND_1_UNICODE45CODEEND_1_UNICODE45CODEEND_1><Gwynn_UNICODE45CODEEND_1_UNICODE45CODEEND_1><params><Base_Strength>9</Base_Strength><Divination_Max_Sd_Mod>100</Divination_Max_Sd_Mod><Dual_Wielding_Mastery>4</Dual_Wielding_Mastery><N_Of_Actions_Percentage>1000000</N_Of_Actions_Percentage><Xp_Gain_Mod>100</Xp_Gain_Mod><Watch_Attack_Others_Mod>100</Watch_Attack_Others_Mod><Gold>302</Gold><Spirit>4</Spirit><Diagonal_Attack_Mod>100</Diagonal_Attack_Mod><Shadow_Mastery_Score>4</Shadow_Mastery_Score><Vigor>100</Vigor><Engaged_Aoo_Defense_Mod>100</Engaged_Aoo_Defense_Mod><Strength>9</Strength><Toughness_Percentage>100</Toughness_Percentage><Base_Spellpower>9</Base_Spellpower><Fortitude>5</Fortitude><Charisma>4</Charisma><Default_Strength>-1</Default_Strength><Defense_Mod>100</Defense_Mod><Watch_Ap_Penalty_Mod>100</Watch_Ap_Penalty_Mod><Instant_Stamina_Penalty>-50</Instant_Stamina_Penalty><Instant_Attack_Mod>100</Instant_Attack_Mod><Sight_Range_Expansion>200</Sight_Range_Expansion><Diagonal_Damage_Mod>100</Diagonal_Damage_Mod><Watch_Defense_Mod>100</Watch_Defense_Mod><Illumination>256.0</Illumination><Endurance>30</Endurance><Instant_Damage_Mod>100</Instant_Damage_Mod><Cadence_Sta_Mod>-25</Cadence_Sta_Mod><Resistance>15</Resistance><Sight_Range>3</Sight_Range><Attr_Points_Per_Level>7.0</Attr_Points_Per_Level><Watch_Defense_Others_Mod>100</Watch_Defense_Others_Mod><Damage_Mod>100</Damage_Mod><Summoned_Xp_Mod>100</Summoned_Xp_Mod><Engaged_Aoo_Attack_Mod>100</Engaged_Aoo_Attack_Mod><Default_Vitality>-1</Default_Vitality><Motivation>50</Motivation><Main_Hand_Gold_Percentage>70</Main_Hand_Gold_Percentage><Witchery_Mastery>7</Witchery_Mastery><Power>48</Power><Force_Knock_Mod>100</Force_Knock_Mod><Endurance_Percentage>100</Endurance_Percentage><Counter_Attack_Mod>100</Counter_Attack_Mod><Default_Dexterity>1</Default_Dexterity><Level>4.0</Level><Counter_Mod>100</Counter_Mod><Mobility_Mastery>7</Mobility_Mastery><Order_Chance_Mod>100</Order_Chance_Mod><Quick_Slots>2</Quick_Slots><Knowledge>7</Knowledge><Interrupt_Damage>100</Interrupt_Damage><C_N_Of_Counters>2</C_N_Of_Counters><Force_Spell_Damage_Mod>100</Force_Spell_Damage_Mod><Explore_Speed>2</Explore_Speed><Damage>10</Damage><Stealth>4</Stealth><Offhand_Attack_Mod>50</Offhand_Attack_Mod><Health>100</Health><Ranged_Penalty_Mod>100</Ranged_Penalty_Mod><Sight_Range_Expansion_Sides>150</Sight_Range_Expansion_Sides><Sneak_Attack_Mod>100</Sneak_Attack_Mod><Aoo_Defense_Mod>100</Aoo_Defense_Mod><Base_Intelligence>9</Base_Intelligence><Carrying_Capacity>50</Carrying_Capacity><Armor_Mod>100</Armor_Mod><Force_Mod_Source_Weight>100</Force_Mod_Source_Weight><Cadence_Ap_Mod>-25</Cadence_Ap_Mod><Divination_Pool_Mod>100</Divination_Pool_Mod><Toughness>15</Toughness><Defense>5</Defense><Force_Push_Mod>100</Force_Push_Mod><Gold_Mod>100</Gold_Mod><Armor_Gold_Percentage>40</Armor_Gold_Percentage><Base_Agility>10</Base_Agility><Watch_Attack_Mod>100</Watch_Attack_Mod><Force_Damage_Mod>100</Force_Damage_Mod><Throw_Attack_Mod>100</Throw_Attack_Mod><Default_Agility>1</Default_Agility><Aoo_Stamina_Penalty>-50</Aoo_Stamina_Penalty><Attr_Points>6</Attr_Points><Total_Xp>486.0</Total_Xp><N_Of_Counters_Percentage>1000000</N_Of_Counters_Percentage><Xp_Level_Mod>100</Xp_Level_Mod><Essence_Percentage>100</Essence_Percentage><Dual_Wielding_Mastery_Score>4</Dual_Wielding_Mastery_Score><Hero_Level>2.0</Hero_Level><Base_Dexterity>10</Base_Dexterity><Girth>350</Girth><Holy_Resistance>15</Holy_Resistance><Force_Mod>100</Force_Mod><Long_Reach_Attack_Mod>100</Long_Reach_Attack_Mod><Attack_Mod>100</Attack_Mod><Dexterity>10</Dexterity><N_Of_Actions>4</N_Of_Actions><Upkeep_Mod>100</Upkeep_Mod><Sneak_Damage_Mod>25</Sneak_Damage_Mod><Travel_Speed>4</Travel_Speed><Blade_Mastery_Score>8</Blade_Mastery_Score><Consumption>1</Consumption><Counter_Stamina_Penalty>-50</Counter_Stamina_Penalty><Starting_Focus>25</Starting_Focus><Mobility_Mastery_Score>7</Mobility_Mastery_Score><Stealth_Mastery_Score>7</Stealth_Mastery_Score><N_Of_Counters>1</N_Of_Counters><Integrity>100</Integrity><Stamina_Percentage>100</Stamina_Percentage><Agility>10</Agility><Sight_Range_Expansion_Backward>200</Sight_Range_Expansion_Backward><Initiative_Modifier>10</Initiative_Modifier><Detection>8</Detection><Shadow_Mastery>4</Shadow_Mastery><Identity_Points_Per_Level>50</Identity_Points_Per_Level><Base_Willpower>6</Base_Willpower><Blade_Mastery>8</Blade_Mastery><Base_Vitality>6</Base_Vitality><Watched_Attack_Mod>100</Watched_Attack_Mod><Long_Reach_Damage_Mod>100</Long_Reach_Damage_Mod><Arcane_Resistance>15</Arcane_Resistance><Focus_Recover_Req>10</Focus_Recover_Req><Oneness>50</Oneness><Base_Wisdom>7</Base_Wisdom><Combat_Readiness>50</Combat_Readiness><Morale_Percentage>1000000</Morale_Percentage><Spellpower>9</Spellpower><Weight>125</Weight><Toughness_Death_Barrier_Mod>100</Toughness_Death_Barrier_Mod><Morale>30</Morale><Attack>5</Attack><Initiative_Percentage>100</Initiative_Percentage><Stealth_Mastery>7</Stealth_Mastery><Identity_Points>3</Identity_Points><Battle_Spirit>100</Battle_Spirit><Free_Masteries>4</Free_Masteries><Wisdom>7</Wisdom><Aoo_Damage_Mod>100</Aoo_Damage_Mod><Xp>280</Xp><Memory_Remaining>4</Memory_Remaining><Sneak_Protection>100</Sneak_Protection><Base_Charisma>4</Base_Charisma><Side_Attack_Mod>100</Side_Attack_Mod><Height>190</Height><Vitality>6</Vitality><Sneak_Defense_Mod>-50</Sneak_Defense_Mod><Base_Damage>3</Base_Damage><Mastery_Points>10</Mastery_Points><Base_Knowledge>7</Base_Knowledge><Extra_Attacks_Point_Cost_Mod>50</Extra_Attacks_Point_Cost_Mod><Initiative_Bonus>5</Initiative_Bonus><Shadow_Resistance>15</Shadow_Resistance><Witchery_Mastery_Score>7</Witchery_Mastery_Score><Focus>100</Focus><Stamina>10</Stamina><Toughness_Recovery>25</Toughness_Recovery><Sneak_Armor_Mod>-25</Sneak_Armor_Mod><Instant_Defense_Mod>100</Instant_Defense_Mod><Side_Damage_Mod>100</Side_Damage_Mod><Close_Quarters_Attack_Mod>100</Close_Quarters_Attack_Mod><Offhand_Damage_Mod>75</Offhand_Damage_Mod><Close_Quarters_Damage_Mod>100</Close_Quarters_Damage_Mod><Counter_Defense_Mod>100</Counter_Defense_Mod><Chaos_Resistance>15</Chaos_Resistance><Willpower>6</Willpower><Aoo_Attack_Mod>100</Aoo_Attack_Mod><C_Morale>30</C_Morale><C_Quick_Slots>4</C_Quick_Slots><C_Stamina>5</C_Stamina><Throw_Damage_Mod>100</Throw_Damage_Mod><Starting_Identity_Points>3</Starting_Identity_Points><Essence>25</Essence><Gold_Per_Level>100</Gold_Per_Level><Engaged_Aoo_Damage_Mod>100</Engaged_Aoo_Damage_Mod><Memorization_Cap>9</Memorization_Cap><Focus_Percentage>100</Focus_Percentage><Organization>100</Organization><Intelligence>9</Intelligence><Mastery_Points_Per_Level>9.0</Mastery_Points_Per_Level></params><props><Image>demo\heroes\gwyn 128.jpg</Image><Classes>Rogue;Trickster;Apostate;</Classes><Quick_Items>Minor Stamina Potion;Minor Healing Potion;Minor Focus Potion</Quick_Items><Id>1049</Id><Displayed_Name>Gwynn</Displayed_Name><Emblem>UI/emblems/auto/free league.png</Emblem><Perks>Surreptitious;</Perks><Type>chars</Type><Group>IGG</Group><Race>Elf</Race><Gender>MALE</Gender><Name>Gwynn - 1 - 1</Name><Main_Hand_Item>Dark Steel Scimitar</Main_Hand_Item><Version>0.9.0c</Version><Spellbook></Spellbook><Inventory><![CDATA[Green Luminescent Fungi (Consumable);Yellow Luminescent Fungi (Consumable);Purple Luminescent Fungi (Consumable);Steel Dagger;Food;Steel Knife]]></Inventory><Natural_Weapon>Petty Fist</Natural_Weapon><Rank>New Hero</Rank><Skills>Greater Dexterity;Short Sword Specialization;</Skills><Known_Spells><![CDATA[Drain Focus;Hallucinations;Malediction;Curse Weapon;Cripple;Enfeeble;Shadow Flame;Fear;Scare;Shadow Bolt;]]></Known_Spells><Armor_Item>Superior Tough Leather Rogue Outfit</Armor_Item><Unique_Id>chars Gwynbleid-4556633272379557649</Unique_Id><Aspect>Neutral</Aspect><Memorized_Spells><![CDATA[Shadow Bolt;Drain Stamina;Drain Focus;Cripple;Enfeeble;Scare;Hallucinations;Drain Life;]]></Memorized_Spells><Mastery_Ranks_1>Blade Mastery;Stealth Mastery;Mobility Mastery;Witchery Mastery;</Mastery_Ranks_1><Offhand_Natural_Weapon>Petty Fist</Offhand_Natural_Weapon><Second_Class>Trickster</Second_Class><Classifications>Humanoid;Hero</Classifications><Jewelry>Minor Bone Ring of Toughness(+15)</Jewelry><Off_Hand_Item>Moon Silver Kris</Off_Hand_Item><Background>Elf</Background><First_Class>Rogue</First_Class><Verbatim_Spells><![CDATA[Shadow Fury CAST black abyss;Shadow Fury CAST black centering;Shadow Fury CAST black centering gravity;Shadow Fury CAST black centering gravity 2;Shadow Fury CAST black cloud;Shadow Fury CAST black cloud 2;Shadow Fury CAST black font;Shadow Fury CAST black fountain;Shadow Fury CAST black gathering;Shadow Fury CAST black grasp 2;Shadow Fury CAST black grasp 3;Shadow Fury CAST black hole hypnotic attached;Shadow Fury CAST black hole hypnotic attached 2;Shadow Fury CAST black pillar;Shadow Fury CAST black pillar 2;Shadow Fury CAST black pillar 3;Shadow Fury CAST black pillar high;Shadow Fury CAST black pit;Shadow Fury CAST black pit 2;Shadow Fury CAST black pool;Shadow Fury CAST black ring;Shadow Fury CAST black swarm;Shadow Fury CAST black veil;Shadow Fury CAST black veil 2;Shadow Fury CAST black waterfall;Shadow Fury CAST black wormhole;Shadow Fury CAST smoke sphere;Shadow Fury CAST smoke sphere hypnotic;Shadow Fury CAST smoke sphere hypnotic attached;Shadow Fury CAST smoke sphere hypnotic large;Shadow Fury CAST smoke sphere hypnotic large 2;Shadow Fury CAST smoke sphere large;Shadow Fury CAST smoke sphere lean;Shadow Fury CAST volumetric fog black;Shadow Fury CAST volumetric fog black 2;Shadow Fury CAST volumetric fog black hypnotic;Shadow Fury CAST volumetric fog blackest;Shadow Fury CAST volumetric fog blackest web;Shadow Fury CAST black missile cone;Shadow Fury CAST black missile cone 2;Shadow Fury CAST black missile cone 3;]]></Verbatim_Spells><Workspace_Group>Test</Workspace_Group><Deity>Faithless</Deity><Principles>Freedom;War;</Principles></props></Gwynn_UNICODE45CODEEND_1_UNICODE45CODEEND_1><Gwynn_UNICODE45CODEEND_1><params><Base_Strength>9</Base_Strength><Divination_Max_Sd_Mod>100</Divination_Max_Sd_Mod><Dual_Wielding_Mastery>4</Dual_Wielding_Mastery><N_Of_Actions_Percentage>1000000</N_Of_Actions_Percentage><Xp_Gain_Mod>100</Xp_Gain_Mod><Watch_Attack_Others_Mod>100</Watch_Attack_Others_Mod><Spirit>4</Spirit><Diagonal_Attack_Mod>100</Diagonal_Attack_Mod><Shadow_Mastery_Score>4</Shadow_Mastery_Score><Vigor>100</Vigor><Engaged_Aoo_Defense_Mod>100</Engaged_Aoo_Defense_Mod><Strength>9</Strength><Toughness_Percentage>100</Toughness_Percentage><Base_Spellpower>9</Base_Spellpower><Fortitude>5</Fortitude><Charisma>4</Charisma><Default_Strength>-1</Default_Strength><Defense_Mod>100</Defense_Mod><Watch_Ap_Penalty_Mod>100</Watch_Ap_Penalty_Mod><Instant_Stamina_Penalty>-50</Instant_Stamina_Penalty><Instant_Attack_Mod>100</Instant_Attack_Mod><Sight_Range_Expansion>200</Sight_Range_Expansion><Diagonal_Damage_Mod>100</Diagonal_Damage_Mod><Watch_Defense_Mod>100</Watch_Defense_Mod><Illumination>256.0</Illumination><Endurance>30</Endurance><Instant_Damage_Mod>100</Instant_Damage_Mod><Cadence_Sta_Mod>-25</Cadence_Sta_Mod><Resistance>15</Resistance><Sight_Range>3</Sight_Range><Attr_Points_Per_Level>6</Attr_Points_Per_Level><Watch_Defense_Others_Mod>100</Watch_Defense_Others_Mod><Damage_Mod>100</Damage_Mod><Summoned_Xp_Mod>100</Summoned_Xp_Mod><Engaged_Aoo_Attack_Mod>100</Engaged_Aoo_Attack_Mod><Default_Vitality>-1</Default_Vitality><Motivation>50</Motivation><Main_Hand_Gold_Percentage>70</Main_Hand_Gold_Percentage><Witchery_Mastery>7</Witchery_Mastery><Power>33</Power><Force_Knock_Mod>100</Force_Knock_Mod><Endurance_Percentage>100</Endurance_Percentage><Counter_Attack_Mod>100</Counter_Attack_Mod><Default_Dexterity>1</Default_Dexterity><Level>2</Level><Counter_Mod>100</Counter_Mod><Mobility_Mastery>7</Mobility_Mastery><Order_Chance_Mod>100</Order_Chance_Mod><Quick_Slots>2</Quick_Slots><Knowledge>7</Knowledge><Interrupt_Damage>100</Interrupt_Damage><C_N_Of_Counters>2</C_N_Of_Counters><Force_Spell_Damage_Mod>100</Force_Spell_Damage_Mod><Explore_Speed>2</Explore_Speed><Damage>10</Damage><Stealth>4</Stealth><Offhand_Attack_Mod>50</Offhand_Attack_Mod><Health>100</Health><Ranged_Penalty_Mod>100</Ranged_Penalty_Mod><Sight_Range_Expansion_Sides>150</Sight_Range_Expansion_Sides><Sneak_Attack_Mod>100</Sneak_Attack_Mod><Aoo_Defense_Mod>100</Aoo_Defense_Mod><Base_Intelligence>9</Base_Intelligence><Carrying_Capacity>50</Carrying_Capacity><Armor_Mod>100</Armor_Mod><Force_Mod_Source_Weight>100</Force_Mod_Source_Weight><Cadence_Ap_Mod>-25</Cadence_Ap_Mod><Divination_Pool_Mod>100</Divination_Pool_Mod><Toughness>15</Toughness><Defense>5</Defense><Force_Push_Mod>100</Force_Push_Mod><Gold_Mod>100</Gold_Mod><Armor_Gold_Percentage>40</Armor_Gold_Percentage><Base_Agility>10</Base_Agility><Watch_Attack_Mod>100</Watch_Attack_Mod><Force_Damage_Mod>100</Force_Damage_Mod><Throw_Attack_Mod>100</Throw_Attack_Mod><Default_Agility>1</Default_Agility><Aoo_Stamina_Penalty>-50</Aoo_Stamina_Penalty><Total_Xp>330</Total_Xp><N_Of_Counters_Percentage>1000000</N_Of_Counters_Percentage><Xp_Level_Mod>100</Xp_Level_Mod><Essence_Percentage>100</Essence_Percentage><Dual_Wielding_Mastery_Score>4</Dual_Wielding_Mastery_Score><Hero_Level>1</Hero_Level><Base_Dexterity>10</Base_Dexterity><Girth>350</Girth><Holy_Resistance>15</Holy_Resistance><Force_Mod>100</Force_Mod><Long_Reach_Attack_Mod>100</Long_Reach_Attack_Mod><Attack_Mod>100</Attack_Mod><Dexterity>10</Dexterity><N_Of_Actions>4</N_Of_Actions><Upkeep_Mod>100</Upkeep_Mod><Sneak_Damage_Mod>25</Sneak_Damage_Mod><Travel_Speed>4</Travel_Speed><Blade_Mastery_Score>8</Blade_Mastery_Score><Consumption>1</Consumption><Counter_Stamina_Penalty>-50</Counter_Stamina_Penalty><Starting_Focus>25</Starting_Focus><Mobility_Mastery_Score>7</Mobility_Mastery_Score><Stealth_Mastery_Score>7</Stealth_Mastery_Score><N_Of_Counters>1</N_Of_Counters><Integrity>100</Integrity><Stamina_Percentage>100</Stamina_Percentage><Agility>10</Agility><Sight_Range_Expansion_Backward>200</Sight_Range_Expansion_Backward><Initiative_Modifier>10</Initiative_Modifier><Detection>8</Detection><Shadow_Mastery>4</Shadow_Mastery><Identity_Points_Per_Level>50</Identity_Points_Per_Level><Base_Willpower>6</Base_Willpower><Blade_Mastery>8</Blade_Mastery><Base_Vitality>6</Base_Vitality><Watched_Attack_Mod>100</Watched_Attack_Mod><Long_Reach_Damage_Mod>100</Long_Reach_Damage_Mod><Arcane_Resistance>15</Arcane_Resistance><Focus_Recover_Req>10</Focus_Recover_Req><Oneness>50</Oneness><Base_Wisdom>7</Base_Wisdom><Combat_Readiness>50</Combat_Readiness><Morale_Percentage>1000000</Morale_Percentage><Spellpower>9</Spellpower><Weight>125</Weight><Toughness_Death_Barrier_Mod>100</Toughness_Death_Barrier_Mod><Morale>30</Morale><Attack>5</Attack><Initiative_Percentage>100</Initiative_Percentage><Stealth_Mastery>7</Stealth_Mastery><Identity_Points>3</Identity_Points><Battle_Spirit>100</Battle_Spirit><Free_Masteries>4</Free_Masteries><Wisdom>7</Wisdom><Aoo_Damage_Mod>100</Aoo_Damage_Mod><Memory_Remaining>4</Memory_Remaining><Sneak_Protection>100</Sneak_Protection><Base_Charisma>4</Base_Charisma><Side_Attack_Mod>100</Side_Attack_Mod><Height>190</Height><Vitality>6</Vitality><Sneak_Defense_Mod>-50</Sneak_Defense_Mod><Base_Damage>3</Base_Damage><Mastery_Points>1</Mastery_Points><Base_Knowledge>7</Base_Knowledge><Extra_Attacks_Point_Cost_Mod>50</Extra_Attacks_Point_Cost_Mod><Initiative_Bonus>5</Initiative_Bonus><Shadow_Resistance>15</Shadow_Resistance><Witchery_Mastery_Score>7</Witchery_Mastery_Score><Focus>100</Focus><Stamina>10</Stamina><Toughness_Recovery>25</Toughness_Recovery><Sneak_Armor_Mod>-25</Sneak_Armor_Mod><Instant_Defense_Mod>100</Instant_Defense_Mod><Side_Damage_Mod>100</Side_Damage_Mod><Close_Quarters_Attack_Mod>100</Close_Quarters_Attack_Mod><Offhand_Damage_Mod>75</Offhand_Damage_Mod><Close_Quarters_Damage_Mod>100</Close_Quarters_Damage_Mod><Counter_Defense_Mod>100</Counter_Defense_Mod><Chaos_Resistance>15</Chaos_Resistance><Willpower>6</Willpower><Aoo_Attack_Mod>100</Aoo_Attack_Mod><C_Morale>30</C_Morale><C_Quick_Slots>4</C_Quick_Slots><C_Stamina>5</C_Stamina><Throw_Damage_Mod>100</Throw_Damage_Mod><Starting_Identity_Points>3</Starting_Identity_Points><Essence>25</Essence><Gold_Per_Level>100</Gold_Per_Level><Engaged_Aoo_Damage_Mod>100</Engaged_Aoo_Damage_Mod><Memorization_Cap>9</Memorization_Cap><Focus_Percentage>100</Focus_Percentage><Organization>100</Organization><Intelligence>9</Intelligence><Mastery_Points_Per_Level>7</Mastery_Points_Per_Level></params><props><Image>demo\heroes\gwyn 128.jpg</Image><Classes>Rogue;Trickster;Apostate;</Classes><Quick_Items>Minor Stamina Potion;Minor Healing Potion;Minor Focus Potion</Quick_Items><Id>1049</Id><Displayed_Name>Gwynn</Displayed_Name><Emblem>UI/emblems/auto/free league.png</Emblem><Perks>Surreptitious;</Perks><Type>chars</Type><Group>IGG</Group><Race>Elf</Race><Gender>MALE</Gender><Name>Gwynn - 1</Name><Main_Hand_Item>Dark Steel Scimitar</Main_Hand_Item><Version>0.9.2c</Version><Spellbook></Spellbook><Inventory><![CDATA[Green Luminescent Fungi (Consumable);Yellow Luminescent Fungi (Consumable);Purple Luminescent Fungi (Consumable);Steel Dagger;Food;Steel Knife]]></Inventory><Natural_Weapon>Petty Fist</Natural_Weapon><Rank>New Hero</Rank><Skills>Greater Dexterity;Short Sword Specialization;</Skills><Known_Spells><![CDATA[Drain Focus;Hallucinations;Malediction;Curse Weapon;Cripple;Enfeeble;Shadow Flame;Fear;Scare;Shadow Bolt;]]></Known_Spells><Armor_Item>Superior Tough Leather Rogue Outfit</Armor_Item><Unique_Id>chars Gwynbleid-4556633272379557649</Unique_Id><Aspect>Neutral</Aspect><Memorized_Spells><![CDATA[Shadow Bolt;Drain Stamina;Drain Focus;Cripple;Enfeeble;Scare;Hallucinations;Drain Life;]]></Memorized_Spells><Mastery_Ranks_1>Blade Mastery;Stealth Mastery;Mobility Mastery;Witchery Mastery;</Mastery_Ranks_1><Offhand_Natural_Weapon>Petty Fist</Offhand_Natural_Weapon><Second_Class>Trickster</Second_Class><Classifications>Humanoid;Hero</Classifications><Jewelry>Minor Bone Ring of Toughness(+15)</Jewelry><Off_Hand_Item>Moon Silver Kris</Off_Hand_Item><Background>Elf</Background><First_Class>Rogue</First_Class><Verbatim_Spells><![CDATA[Shadow Fury CAST black abyss;Shadow Fury CAST black centering;Shadow Fury CAST black centering gravity;Shadow Fury CAST black centering gravity 2;Shadow Fury CAST black cloud;Shadow Fury CAST black cloud 2;Shadow Fury CAST black font;Shadow Fury CAST black fountain;Shadow Fury CAST black gathering;Shadow Fury CAST black grasp 2;Shadow Fury CAST black grasp 3;Shadow Fury CAST black hole hypnotic attached;Shadow Fury CAST black hole hypnotic attached 2;Shadow Fury CAST black pillar;Shadow Fury CAST black pillar 2;Shadow Fury CAST black pillar 3;Shadow Fury CAST black pillar high;Shadow Fury CAST black pit;Shadow Fury CAST black pit 2;Shadow Fury CAST black pool;Shadow Fury CAST black ring;Shadow Fury CAST black swarm;Shadow Fury CAST black veil;Shadow Fury CAST black veil 2;Shadow Fury CAST black waterfall;Shadow Fury CAST black wormhole;Shadow Fury CAST smoke sphere;Shadow Fury CAST smoke sphere hypnotic;Shadow Fury CAST smoke sphere hypnotic attached;Shadow Fury CAST smoke sphere hypnotic large;Shadow Fury CAST smoke sphere hypnotic large 2;Shadow Fury CAST smoke sphere large;Shadow Fury CAST smoke sphere lean;Shadow Fury CAST volumetric fog black;Shadow Fury CAST volumetric fog black 2;Shadow Fury CAST volumetric fog black hypnotic;Shadow Fury CAST volumetric fog blackest;Shadow Fury CAST volumetric fog blackest web;Shadow Fury CAST black missile cone;Shadow Fury CAST black missile cone 2;Shadow Fury CAST black missile cone 3;]]></Verbatim_Spells><Workspace_Group>Test</Workspace_Group><Deity>Faithless</Deity><Principles>Freedom;War;</Principles></props></Gwynn_UNICODE45CODEEND_1></Elf></XML>