<Level><Custom_Props><Workspace_Group>IMPLEMENT</Workspace_Group>
<Dungeon_Main_Entrances>Eerie Portal(9-7);Heavy Doors(14-4)</Dungeon_Main_Entrances>
<Dungeon_Subfolder>demo</Dungeon_Subfolder>
<Map_Background>main\background\Ironhelm Tunnel.png</Map_Background>
</Custom_Props><Custom_Params><Bf_Width>15</Bf_Width>
<Bf_Height>11</Bf_Height>
</Custom_Params><Wall_Objects></Wall_Objects>
<Direction_Map>3-2=Magic Circles(UP);3-6=Magic Circles(DOWN);0-7=Fiery Skull(RIGHT);11-3=Rune Inscription(DOWN_LEFT);11-5=Rune Inscription(UP_LEFT);5-2=Magic Circles(UP);2-3=Magic Circles(LEFT);5-6=Magic Circles(DOWN);2-5=Magic Circles(LEFT);5-8=Fiery Skull(RIGHT);12-2=Magic Circles(DOWN);9-3=Rune Inscription(DOWN_RIGHT);12-6=Magic Circles(UP);9-5=Rune Inscription(UP_RIGHT);</Direction_Map>
<Plan><Dungeon_Type>Dungeon</Dungeon_Type>
<Zones><Zone_UNICODE35CODEEND0UNICODE44CODEEND_X0UNICODE45CODEEND15UNICODE59CODEEND_Y0UNICODE45CODEEND11><Blocks><RoomUNICODE45CODEEND0><Block_Type>Room</Block_Type>
<Coordinates>14-10;14-9;14-8;14-7;14-6;14-5;14-4;14-3;14-2;14-1;14-0;13-10;13-9;13-8;13-7;13-6;13-5;13-4;13-3;13-2;13-1;13-0;12-10;12-9;12-8;12-7;12-6;12-5;12-4;12-3;12-2;12-1;12-0;11-10;11-9;11-8;11-7;11-6;11-5;11-4;11-3;11-2;11-1;11-0;10-10;10-9;10-8;10-7;10-6;10-5;10-4;10-3;10-2;10-1;10-0;9-10;9-9;9-8;9-7;9-6;9-5;9-4;9-3;9-2;9-1;9-0;8-10;8-9;8-8;8-7;8-6;8-5;8-4;8-3;8-2;8-1;8-0;7-10;7-9;7-8;7-7;7-6;7-5;7-4;7-3;7-2;7-1;7-0;6-10;6-9;6-8;6-7;6-6;6-5;6-4;6-3;6-2;6-1;6-0;5-10;5-9;5-8;5-7;5-6;5-5;5-4;5-3;5-2;5-1;5-0;4-10;4-9;4-8;4-7;4-6;4-5;4-4;4-3;4-2;4-1;4-0;3-10;3-9;3-8;3-7;3-6;3-5;3-4;3-3;3-2;3-1;3-0;2-10;2-9;2-8;2-7;2-6;2-5;2-4;2-3;2-2;2-1;2-0;1-10;1-9;1-8;1-7;1-6;1-5;1-4;1-3;1-2;1-1;1-0;0-10;0-9;0-8;0-7;0-6;0-5;0-4;0-3;0-2;0-1;0-0;</Coordinates><Objects>0-1=Stone Wall,0-3=Stone Wall,0-4=Stone Wall,0-5=Stone Wall,0-6=Stone Wall,0-7=Stone Wall,0-7=Fiery Skull,0-8=Stone Wall,0-9=Cave Wall,1-0=Stone Wall,0-10=Cave Wall,2-0=Stone Wall,2-2=Stone Wall,2-3=Stone Wall,2-3=Magic Circles,2-4=Stone Door,2-5=Stone Wall,2-5=Magic Circles,2-6=Stone Wall,2-8=Stone Wall,2-9=Stone Wall,3-0=Stone Wall,2-10=Cave Wall,3-2=Stone Wall,3-2=Magic Circles,3-6=Stone Wall,3-6=Magic Circles,4-0=Stone Wall,3-10=Stone Wall,4-2=Stone Door,4-4=Witchfire Brazier,4-6=Stone Door,4-8=Stone Wall,5-0=Stone Wall,4-10=Stone Wall,5-2=Stone Wall,5-2=Magic Circles,5-3=Skull Pile,5-6=Stone Wall,5-6=Magic Circles,5-8=Stone Wall,5-8=Fiery Skull,6-0=Stone Wall,5-10=Stone Wall,6-2=Stone Wall,6-3=Stone Wall,6-4=Stone Door,6-5=Stone Wall,6-6=Stone Wall,7-0=Stone Wall,6-10=Stone Wall,7-3=Stone Wall,7-4=Treasure Pile,7-5=Stone Wall,7-8=Steel Masked Cultist,8-0=Stone Wall,7-10=Stone Wall,8-3=Stone Wall,8-4=Silver Chest,8-5=Stone Wall,8-7=Stone Wall,8-9=Stone Wall,9-0=Stone Wall,9-3=Stone Wall,9-3=Rune Inscription,9-4=Stone Door,9-5=Stone Wall,9-5=Rune Inscription,9-6=Stone Wall,9-7=Eerie Portal,10-0=Stone Wall,9-10=Stone Wall,10-3=Stone Door,10-4=Cerberus,10-5=Stone Door,10-7=Stone Wall,11-0=Stone Wall,10-10=Stone Wall,11-3=Stone Wall,11-3=Rune Inscription,11-4=Stone Door,11-5=Stone Wall,11-5=Rune Inscription,11-6=Steel Masked Cultist,12-0=Stone Wall,11-10=Stone Wall,12-1=Worm Masked Cultist,12-2=Stone Wall,12-2=Magic Circles,12-3=Eldritch Rod,12-5=Eldritch Rod,12-6=Stone Wall,12-6=Magic Circles,12-7=Stone Wall,13-0=Stone Wall,12-10=Stone Wall,13-2=Stone Wall,13-4=Mistborn Gargantuan,13-6=Stone Wall,13-8=Onyx Masked Cultist,13-10=Stone Wall,14-1=Stone Wall,14-4=Heavy Doors,14-7=Stone Wall,14-8=Stone Wall,14-9=Stone Wall,</Objects></RoomUNICODE45CODEEND0></Blocks></Zone_UNICODE35CODEEND0UNICODE44CODEEND_X0UNICODE45CODEEND15UNICODE59CODEEND_Y0UNICODE45CODEEND11></Zones><Entrances>Center</Entrances><Exits>Center East</Exits></Plan></Level>