<Party><Kali><params><Resistance>15</Resistance><Mastery_Points_Per_Level>5</Mastery_Points_Per_Level><Default_Charisma>1</Default_Charisma><Essence>25</Essence><Knowledge>8</Knowledge><Summoned_Xp_Mod>100</Summoned_Xp_Mod><N_Of_Actions_Percentage>1000000</N_Of_Actions_Percentage><Base_Damage>3</Base_Damage><Willpower>5</Willpower><Xp>7</Xp><Base_Charisma>6</Base_Charisma><Focus>100</Focus><Stamina_Percentage>100</Stamina_Percentage><Morale_Percentage>1000000</Morale_Percentage><Intelligence>5</Intelligence><Detection_Mastery>1</Detection_Mastery><Default_Vitality>-1</Default_Vitality><Attr_Points_Per_Level>5</Attr_Points_Per_Level><Base_Intelligence>5</Base_Intelligence><Carrying_Capacity>50</Carrying_Capacity><Base_Strength>3</Base_Strength><Detection_Mastery_Score>1</Detection_Mastery_Score><N_Of_Actions>4</N_Of_Actions><Charisma>6</Charisma><Default_Agility>1</Default_Agility><Starting_Focus>25</Starting_Focus><Chaos_Resistance>15</Chaos_Resistance><Gold_Mod>100</Gold_Mod><Free_Masteries>5</Free_Masteries><Base_Dexterity>10</Base_Dexterity><Base_Vitality>6</Base_Vitality><Stealth>4</Stealth><Spellpower>7</Spellpower><Offhand_Attack_Mod>50</Offhand_Attack_Mod><Stamina>10</Stamina><Mobility_Mastery_Score>5</Mobility_Mastery_Score><Main_Hand_Gold_Percentage>70</Main_Hand_Gold_Percentage><Cadence_Sta_Mod>-35</Cadence_Sta_Mod><Toughness>15</Toughness><Armor_Mod>100</Armor_Mod><Toughness_Percentage>100</Toughness_Percentage><Power>22</Power><Counter_Mod>50</Counter_Mod><Interrupt_Damage>100</Interrupt_Damage><Arcane_Resistance>15</Arcane_Resistance><Upkeep_Mod>100</Upkeep_Mod><Acid_Resistance>25</Acid_Resistance><N_Of_Counters_Percentage>1000000</N_Of_Counters_Percentage><Endurance_Percentage>100</Endurance_Percentage><Endurance>30</Endurance><Base_Knowledge>8</Base_Knowledge><Vitality>6</Vitality><Quick_Slots>2</Quick_Slots><Memory_Remaining>4</Memory_Remaining><Mobility_Mastery>5</Mobility_Mastery><Weight>125</Weight><Detection>18</Detection><C_Quick_Slots>4</C_Quick_Slots><Default_Wisdom>1</Default_Wisdom><Offhand_Damage_Mod>75</Offhand_Damage_Mod><Focus_Percentage>100</Focus_Percentage><Base_Agility>6</Base_Agility><Attack>5</Attack><Damage_Mod>100</Damage_Mod><Total_Xp>225</Total_Xp><Base_Wisdom>6</Base_Wisdom><Xp_Gain_Mod>100</Xp_Gain_Mod><Default_Strength>-2</Default_Strength><Xp_Level_Mod>100</Xp_Level_Mod><Morale>30</Morale><N_Of_Counters>1</N_Of_Counters><Light_Resistance>15</Light_Resistance><Initiative_Bonus>5</Initiative_Bonus><Divination_Max_Sd_Mod>100</Divination_Max_Sd_Mod><Holy_Resistance>10</Holy_Resistance><Initiative_Percentage>100</Initiative_Percentage><Wisdom>6</Wisdom><Sight_Range>3</Sight_Range><Essence_Percentage>100</Essence_Percentage><Base_Willpower>5</Base_Willpower><Divination_Pool_Mod>100</Divination_Pool_Mod><Damage>10</Damage><Strength>3</Strength><Dexterity>10</Dexterity><Gold>7</Gold><Meditation_Mastery>5</Meditation_Mastery><Spirit>4</Spirit><Level>2</Level><Default_Dexterity>2</Default_Dexterity><Defense_Mod>100</Defense_Mod><Elemental_Mastery_Score>10</Elemental_Mastery_Score><Defense>5</Defense><Polearm_Mastery_Score>2</Polearm_Mastery_Score><Fire_Resistance>15</Fire_Resistance><Meditation_Mastery_Score>5</Meditation_Mastery_Score><Cold_Resistance>25</Cold_Resistance><Agility>6</Agility><Polearm_Mastery>2</Polearm_Mastery><Cadence_Ap_Mod>-25</Cadence_Ap_Mod><Lightning_Resistance>25</Lightning_Resistance><Elemental_Mastery>10</Elemental_Mastery><Initiative_Modifier>10</Initiative_Modifier><Memorization_Cap>5</Memorization_Cap><Base_Spellpower>7</Base_Spellpower><Attack_Mod>100</Attack_Mod><Armor_Gold_Percentage>40</Armor_Gold_Percentage></params><props><Verbatim_Spells>Gush;</Verbatim_Spells><Group>Preset</Group><Race>Elf</Race><Emblem>UI\emblems\std\life\Faerie Queen.jpg</Emblem><Memorized_Spells>Fire Bolt;Gust of Wind;</Memorized_Spells><Displayed_Name>Kali</Displayed_Name><Type>chars</Type><Rank>New Hero</Rank><Aspect>Life</Aspect><Skills>Stillness;Sidestep;</Skills><Quick_Items>Minor Fortifying Potion;Minor Stamina Potion;</Quick_Items><Natural_Weapon>Petty Fist</Natural_Weapon><Background>Fey Elf</Background><Armor_Item>Inferior Cotton Druid Robe</Armor_Item><Known_Spells>Fire Bolt;Gush;Gust of Wind;</Known_Spells><Jewelry></Jewelry><Principles>Freedom;Peace;</Principles><Spellbook></Spellbook><Deity>Fey Queen</Deity><Main_Hand_Item>Inferior Palewood Staff</Main_Hand_Item><Name>Kali</Name><Inventory></Inventory><Classifications>Humanoid;Hero</Classifications><Off_Hand_Item>Inferior Onyx Orb</Off_Hand_Item><Soundset>chars\female\wood elf\</Soundset><Offhand_Natural_Weapon>Petty Fist</Offhand_Natural_Weapon><Gender>FEMALE</Gender><Image>\mini\char\std\elf\fey\w_Elf.jpg</Image></props></Kali><Memnon><params><Resistance>15</Resistance><Mastery_Points_Per_Level>5</Mastery_Points_Per_Level><Default_Charisma>2</Default_Charisma><Essence>25</Essence><Knowledge>10</Knowledge><Summoned_Xp_Mod>100</Summoned_Xp_Mod><Savage_Mastery_Score>1</Savage_Mastery_Score><N_Of_Actions_Percentage>1000000</N_Of_Actions_Percentage><Base_Damage>3</Base_Damage><Willpower>5</Willpower><Xp>14</Xp><Base_Charisma>8</Base_Charisma><Focus>100</Focus><Stamina_Percentage>100</Stamina_Percentage><Morale_Percentage>1000000</Morale_Percentage><Intelligence>9</Intelligence><Default_Vitality>-1</Default_Vitality><Attr_Points_Per_Level>5</Attr_Points_Per_Level><Base_Intelligence>9</Base_Intelligence><Carrying_Capacity>65</Carrying_Capacity><Base_Strength>4</Base_Strength><N_Of_Actions>4</N_Of_Actions><Charisma>8</Charisma><Starting_Focus>25</Starting_Focus><Chaos_Resistance>15</Chaos_Resistance><Gold_Mod>100</Gold_Mod><Shadow_Resistance>15</Shadow_Resistance><Free_Masteries>6</Free_Masteries><Base_Dexterity>5</Base_Dexterity><Base_Vitality>4</Base_Vitality><Stealth>5</Stealth><Spellpower>7</Spellpower><Offhand_Attack_Mod>50</Offhand_Attack_Mod><Stamina>10</Stamina><Main_Hand_Gold_Percentage>70</Main_Hand_Gold_Percentage><Cadence_Sta_Mod>-35</Cadence_Sta_Mod><Toughness>15</Toughness><Armor_Mod>100</Armor_Mod><Toughness_Percentage>100</Toughness_Percentage><Power>22</Power><Counter_Mod>50</Counter_Mod><Interrupt_Damage>100</Interrupt_Damage><Arcane_Resistance>15</Arcane_Resistance><Upkeep_Mod>100</Upkeep_Mod><N_Of_Counters_Percentage>1000000</N_Of_Counters_Percentage><Endurance_Percentage>100</Endurance_Percentage><Endurance>30</Endurance><Base_Knowledge>10</Base_Knowledge><Vitality>4</Vitality><Quick_Slots>2</Quick_Slots><Memory_Remaining>4</Memory_Remaining><Weight>125</Weight><Detection>15</Detection><C_Quick_Slots>4</C_Quick_Slots><Default_Wisdom>3</Default_Wisdom><Offhand_Damage_Mod>75</Offhand_Damage_Mod><Focus_Percentage>100</Focus_Percentage><Base_Agility>5</Base_Agility><Attack>5</Attack><Damage_Mod>100</Damage_Mod><Total_Xp>225</Total_Xp><Xp_Gain_Mod>100</Xp_Gain_Mod><Base_Wisdom>8</Base_Wisdom><Divination_Mastery>7</Divination_Mastery><Default_Strength>-1</Default_Strength><Xp_Level_Mod>100</Xp_Level_Mod><Morale>30</Morale><N_Of_Counters>1</N_Of_Counters><Default_Spellpower>2</Default_Spellpower><Initiative_Bonus>5</Initiative_Bonus><Divination_Max_Sd_Mod>100</Divination_Max_Sd_Mod><Holy_Resistance>15</Holy_Resistance><Sylvan_Mastery>10</Sylvan_Mastery><Default_Knowledge>2</Default_Knowledge><Initiative_Percentage>100</Initiative_Percentage><Wisdom>8</Wisdom><Sight_Range>3</Sight_Range><Essence_Percentage>100</Essence_Percentage><Base_Willpower>5</Base_Willpower><Divination_Pool_Mod>100</Divination_Pool_Mod><Damage>10</Damage><Strength>4</Strength><Dexterity>5</Dexterity><Gold>24</Gold><Meditation_Mastery>5</Meditation_Mastery><Spirit>4</Spirit><Level>2</Level><Defense_Mod>100</Defense_Mod><Elemental_Mastery_Score>2</Elemental_Mastery_Score><Defense>5</Defense><Meditation_Mastery_Score>5</Meditation_Mastery_Score><Agility>5</Agility><Savage_Mastery>1</Savage_Mastery><Cadence_Ap_Mod>-25</Cadence_Ap_Mod><Elemental_Mastery>2</Elemental_Mastery><Side_Sight_Penalty>-1</Side_Sight_Penalty><Initiative_Modifier>10</Initiative_Modifier><Divination_Mastery_Score>7</Divination_Mastery_Score><Memorization_Cap>5</Memorization_Cap><Base_Spellpower>7</Base_Spellpower><Attack_Mod>100</Attack_Mod><Sylvan_Mastery_Score>10</Sylvan_Mastery_Score><Armor_Gold_Percentage>40</Armor_Gold_Percentage></params><props><Group>Preset</Group><Race>Elf</Race><Description></Description><Emblem>UI\emblems\std\life\druid.jpg</Emblem><Memorized_Spells>Rapid Growth;Fortify;Cure;</Memorized_Spells><Classes>Hermit;</Classes><Displayed_Name>Memnon</Displayed_Name><Type>chars</Type><Rank>New Hero</Rank><Aspect>Life</Aspect><Skills>Nature Empathy;Stillness;</Skills><Quick_Items></Quick_Items><Natural_Weapon>Average Fist</Natural_Weapon><Background>Wood Elf</Background><Armor_Item>Inferior Cotton Druid Robe</Armor_Item><Base_Type>Wood Elf Seer</Base_Type><Known_Spells>Cure;Fortify;Rapid Growth;Gush;Predator Instincts;Gust of Wind;</Known_Spells><Jewelry>Minor Power Ring of Vitality(+2);</Jewelry><Principles>Peace;Tradition;</Principles><First_Class>Hermit</First_Class><Spellbook>Gush;Predator Instincts;Gust of Wind;</Spellbook><Deity>World Tree</Deity><Main_Hand_Item></Main_Hand_Item><Name>Memnon</Name><Inventory></Inventory><Off_Hand_Item></Off_Hand_Item><Classifications>Humanoid;Hero</Classifications><Lore></Lore><Soundset>chars\male\trickster\</Soundset><Offhand_Natural_Weapon>Average Fist</Offhand_Natural_Weapon><Gender>MALE</Gender><Version>0.1001</Version><Standard_Passives></Standard_Passives><Image>\mini\char\std\elf\wood\L_WE_M_01.jpg</Image></props></Memnon><Tili><params><Resistance>15</Resistance><Mastery_Points_Per_Level>5</Mastery_Points_Per_Level><Default_Charisma>-1</Default_Charisma><Essence>25</Essence><Knowledge>3</Knowledge><Summoned_Xp_Mod>100</Summoned_Xp_Mod><N_Of_Actions_Percentage>1000000</N_Of_Actions_Percentage><Base_Damage>3</Base_Damage><Willpower>6</Willpower><Xp>4</Xp><Base_Charisma>4</Base_Charisma><Water_Resistance>25</Water_Resistance><Focus>100</Focus><Stamina_Percentage>100</Stamina_Percentage><Morale_Percentage>1000000</Morale_Percentage><Intelligence>4</Intelligence><Default_Vitality>4</Default_Vitality><Base_Intelligence>4</Base_Intelligence><Attr_Points_Per_Level>5</Attr_Points_Per_Level><Carrying_Capacity>65</Carrying_Capacity><Base_Strength>12</Base_Strength><N_Of_Actions>4</N_Of_Actions><Charisma>4</Charisma><Starting_Focus>25</Starting_Focus><Gold_Mod>100</Gold_Mod><Free_Masteries>6</Free_Masteries><Base_Dexterity>5</Base_Dexterity><Base_Vitality>9</Base_Vitality><Spellpower>3</Spellpower><Offhand_Attack_Mod>50</Offhand_Attack_Mod><Stamina>10</Stamina><Main_Hand_Gold_Percentage>70</Main_Hand_Gold_Percentage><Cadence_Sta_Mod>-35</Cadence_Sta_Mod><Toughness>15</Toughness><Earth_Resistance>35</Earth_Resistance><Armor_Mod>100</Armor_Mod><Toughness_Percentage>100</Toughness_Percentage><Power>22</Power><Counter_Mod>50</Counter_Mod><Interrupt_Damage>100</Interrupt_Damage><Upkeep_Mod>100</Upkeep_Mod><Dual_Wielding_Mastery>2</Dual_Wielding_Mastery><Two_Handed_Mastery_Score>10</Two_Handed_Mastery_Score><N_Of_Counters_Percentage>1000000</N_Of_Counters_Percentage><Endurance_Percentage>100</Endurance_Percentage><Endurance>30</Endurance><Base_Knowledge>3</Base_Knowledge><Vitality>9</Vitality><Quick_Slots>2</Quick_Slots><Memory_Remaining>4</Memory_Remaining><Weight>175</Weight><Slashing_Resistance>25</Slashing_Resistance><Detection>10</Detection><C_Quick_Slots>4</C_Quick_Slots><Offhand_Damage_Mod>75</Offhand_Damage_Mod><Focus_Percentage>100</Focus_Percentage><Base_Agility>10</Base_Agility><Athletics_Mastery_Score>3</Athletics_Mastery_Score><Attack>5</Attack><Damage_Mod>100</Damage_Mod><Total_Xp>225</Total_Xp><Base_Wisdom>5</Base_Wisdom><Xp_Gain_Mod>100</Xp_Gain_Mod><Default_Strength>3</Default_Strength><Xp_Level_Mod>100</Xp_Level_Mod><Morale>30</Morale><N_Of_Counters>1</N_Of_Counters><Default_Spellpower>-2</Default_Spellpower><Initiative_Bonus>5</Initiative_Bonus><Divination_Max_Sd_Mod>100</Divination_Max_Sd_Mod><Default_Intelligence>-1</Default_Intelligence><Default_Knowledge>-2</Default_Knowledge><Initiative_Percentage>100</Initiative_Percentage><Wisdom>5</Wisdom><Sight_Range>3</Sight_Range><Essence_Percentage>100</Essence_Percentage><Base_Willpower>6</Base_Willpower><Divination_Pool_Mod>100</Divination_Pool_Mod><Damage>10</Damage><Two_Handed_Mastery>10</Two_Handed_Mastery><Strength>12</Strength><Dexterity>5</Dexterity><Axe_Mastery_Score>10</Axe_Mastery_Score><Gold>9</Gold><Athletics_Mastery>3</Athletics_Mastery><Spirit>4</Spirit><Bludgeoning_Resistance>25</Bludgeoning_Resistance><Level>2</Level><Default_Dexterity>-1</Default_Dexterity><Defense_Mod>100</Defense_Mod><Defense>5</Defense><Axe_Mastery>10</Axe_Mastery><Fire_Resistance>25</Fire_Resistance><Agility>10</Agility><Default_Willpower>1</Default_Willpower><Dual_Wielding_Mastery_Score>2</Dual_Wielding_Mastery_Score><Cadence_Ap_Mod>-25</Cadence_Ap_Mod><Side_Sight_Penalty>1</Side_Sight_Penalty><Initiative_Modifier>10</Initiative_Modifier><Memorization_Cap>5</Memorization_Cap><Base_Spellpower>3</Base_Spellpower><Attack_Mod>100</Attack_Mod><Armor_Gold_Percentage>40</Armor_Gold_Percentage></params><props><Group>Preset</Group><Race>Dwarf</Race><Emblem>UI\emblems\std\neutral\ax.jpg</Emblem><Classes>Fighter;</Classes><Displayed_Name>Tili</Displayed_Name><Type>chars</Type><Rank>New Hero</Rank><Quick_Items></Quick_Items><Natural_Weapon>Average Fist</Natural_Weapon><Background>Wildaxe Dwarf</Background><Armor_Item></Armor_Item><Jewelry></Jewelry><Known_Spells></Known_Spells><Principles>Honor;Freedom;</Principles><First_Class>Fighter</First_Class><Spellbook></Spellbook><Deity>Wild God</Deity><Main_Hand_Item>Inferior Iron Great Axe</Main_Hand_Item><Name>Tili</Name><Inventory></Inventory><Off_Hand_Item></Off_Hand_Item><Classifications>Humanoid;Hero</Classifications><Soundset>Dwarf</Soundset><Offhand_Natural_Weapon>Average Fist</Offhand_Natural_Weapon><Gender>MALE</Gender><Image>\mini\char\std\dwarf\\Dwarf (2).jpg</Image></props></Tili><Exilyon><params><Poison_Resistance>15</Poison_Resistance><Resistance>15</Resistance><Mastery_Points_Per_Level>5</Mastery_Points_Per_Level><Essence>25</Essence><Knowledge>5</Knowledge><Summoned_Xp_Mod>100</Summoned_Xp_Mod><N_Of_Actions_Percentage>1000000</N_Of_Actions_Percentage><Base_Damage>3</Base_Damage><Willpower>6</Willpower><Xp>28</Xp><Base_Charisma>6</Base_Charisma><Focus>100</Focus><Stamina_Percentage>100</Stamina_Percentage><Blade_Mastery_Score>4</Blade_Mastery_Score><Morale_Percentage>1000000</Morale_Percentage><Intelligence>6</Intelligence><Detection_Mastery>2</Detection_Mastery><Default_Vitality>-1</Default_Vitality><Attr_Points_Per_Level>5</Attr_Points_Per_Level><Base_Intelligence>6</Base_Intelligence><Carrying_Capacity>65</Carrying_Capacity><Base_Strength>6</Base_Strength><Detection_Mastery_Score>2</Detection_Mastery_Score><N_Of_Actions>4</N_Of_Actions><Charisma>6</Charisma><Default_Agility>2</Default_Agility><Starting_Focus>25</Starting_Focus><Gold_Mod>100</Gold_Mod><Shadow_Resistance>25</Shadow_Resistance><Marksmanship_Mastery_Score>10</Marksmanship_Mastery_Score><Free_Masteries>5</Free_Masteries><Base_Dexterity>8</Base_Dexterity><Base_Vitality>8</Base_Vitality><Stealth>5</Stealth><Spellpower>5</Spellpower><Offhand_Attack_Mod>50</Offhand_Attack_Mod><Stamina>10</Stamina><Mobility_Mastery_Score>10</Mobility_Mastery_Score><Main_Hand_Gold_Percentage>70</Main_Hand_Gold_Percentage><Cadence_Sta_Mod>-35</Cadence_Sta_Mod><Toughness>15</Toughness><Armor_Mod>100</Armor_Mod><Toughness_Percentage>100</Toughness_Percentage><Power>22</Power><Counter_Mod>50</Counter_Mod><Interrupt_Damage>100</Interrupt_Damage><Arcane_Resistance>15</Arcane_Resistance><Marksmanship_Mastery>10</Marksmanship_Mastery><Upkeep_Mod>100</Upkeep_Mod><Stealth_Mastery>2</Stealth_Mastery><N_Of_Counters_Percentage>1000000</N_Of_Counters_Percentage><Endurance_Percentage>100</Endurance_Percentage><Endurance>30</Endurance><Base_Knowledge>5</Base_Knowledge><Vitality>8</Vitality><Quick_Slots>2</Quick_Slots><Mobility_Mastery>10</Mobility_Mastery><Memory_Remaining>4</Memory_Remaining><Weight>125</Weight><Detection>15</Detection><C_Quick_Slots>4</C_Quick_Slots><Offhand_Damage_Mod>75</Offhand_Damage_Mod><Focus_Percentage>100</Focus_Percentage><Base_Agility>11</Base_Agility><Attack>5</Attack><Damage_Mod>100</Damage_Mod><Total_Xp>225</Total_Xp><Base_Wisdom>5</Base_Wisdom><Xp_Gain_Mod>100</Xp_Gain_Mod><Xp_Level_Mod>100</Xp_Level_Mod><Morale>30</Morale><N_Of_Counters>1</N_Of_Counters><Initiative_Bonus>5</Initiative_Bonus><Divination_Max_Sd_Mod>100</Divination_Max_Sd_Mod><Holy_Resistance>15</Holy_Resistance><Default_Intelligence>1</Default_Intelligence><Initiative_Percentage>100</Initiative_Percentage><Wisdom>5</Wisdom><Sight_Range>3</Sight_Range><Essence_Percentage>100</Essence_Percentage><Base_Willpower>6</Base_Willpower><Divination_Pool_Mod>100</Divination_Pool_Mod><Damage>10</Damage><Strength>6</Strength><Dexterity>8</Dexterity><Gold>1</Gold><Spirit>4</Spirit><Level>2</Level><Default_Dexterity>3</Default_Dexterity><Defense_Mod>100</Defense_Mod><Stealth_Mastery_Score>2</Stealth_Mastery_Score><Defense>5</Defense><Agility>11</Agility><Default_Willpower>1</Default_Willpower><Blade_Mastery>4</Blade_Mastery><Cadence_Ap_Mod>-25</Cadence_Ap_Mod><Side_Sight_Penalty>-1</Side_Sight_Penalty><Initiative_Modifier>10</Initiative_Modifier><Memorization_Cap>5</Memorization_Cap><Base_Spellpower>5</Base_Spellpower><Attack_Mod>100</Attack_Mod><Armor_Gold_Percentage>40</Armor_Gold_Percentage></params><props><Group>Preset</Group><Race>Elf</Race><Description></Description><Emblem>UI\emblems\std\neutral\xp2_textures_bif-0000000228.jpg</Emblem><Displayed_Name>Exilyon</Displayed_Name><Type>chars</Type><Rank>New Hero</Rank><Aspect>Neutral</Aspect><Skills>Sidestep;Quick Turn;Bow Specialization;</Skills><Quick_Items>Superior Iron Arrows;</Quick_Items><Natural_Weapon>Average Fist</Natural_Weapon><Background>Grey Elf</Background><Armor_Item>Inferior Thin Leather Rogue Outfit</Armor_Item><Base_Type>Grey Elf Mistguard</Base_Type><Known_Spells></Known_Spells><Jewelry></Jewelry><Principles>Freedom;Tradition;</Principles><Spellbook></Spellbook><Deity>Faithless</Deity><Main_Hand_Item>Inferior Palewood Short Bow</Main_Hand_Item><Name>Exilyon</Name><Inventory></Inventory><Off_Hand_Item>Inferior Copper Knife</Off_Hand_Item><Classifications>Humanoid;Hero</Classifications><Lore></Lore><Soundset>chars\male\rogue\</Soundset><Offhand_Natural_Weapon>Average Fist</Offhand_Natural_Weapon><Gender>MALE</Gender><Version>0.1001</Version><Standard_Passives></Standard_Passives><Image>\mini\char\std\elf\grey\grey elf ranger.jpg</Image></props></Exilyon></Party>