<Party><Sir_Richard><params><Endurance_Regen>0</Endurance_Regen>
<Focus_Penalty>0</Focus_Penalty>
<Stamina>10</Stamina>
<Default_Agility>5</Default_Agility>
<Rest_Bonus>0</Rest_Bonus>
<Meditation_Bonus>0</Meditation_Bonus>
<Morale_Percentage>1000000</Morale_Percentage>
<Stamina_Percentage>100</Stamina_Percentage>
<Action_Points_Remaining>0</Action_Points_Remaining>
<Cooldown_Mod>0</Cooldown_Mod>
<Athletics_Mastery>0</Athletics_Mastery>
<C_Quick_Slots>4</C_Quick_Slots>
<Spell_Ap_Penalty>0</Spell_Ap_Penalty>
<Behind_Sight_Bonus>0</Behind_Sight_Bonus>
<Slashing_Resistance>0</Slashing_Resistance>
<Base_Strength>9</Base_Strength>
<Attack_Mod>100</Attack_Mod>
<Agility>5</Agility>
<Initiative_Modifier>10</Initiative_Modifier>
<Wizardry_Mastery>0</Wizardry_Mastery>
<Blood_Magic_Mastery>0</Blood_Magic_Mastery>
<Initiative_Percentage>100</Initiative_Percentage>
<Xp>519</Xp>
<Side_Sight_Penalty>1</Side_Sight_Penalty>
<Spell_Foc_Penalty>0</Spell_Foc_Penalty>
<Chaos_Resistance>0</Chaos_Resistance>
<Carrying_Capacity>200</Carrying_Capacity>
<Bludgeoning_Resistance>0</Bludgeoning_Resistance>
<Xp_Cost_Reduction_Verbatim_Spells>0</Xp_Cost_Reduction_Verbatim_Spells>
<C_Initiative_Bonus>0</C_Initiative_Bonus>
<Mobility_Mastery>0</Mobility_Mastery>
<Armor>0</Armor>
<Arcane_Resistance>0</Arcane_Resistance>
<Shadow_Resistance>0</Shadow_Resistance>
<Xp_Gain_Mod>100</Xp_Gain_Mod>
<Essence_Penalty>0</Essence_Penalty>
<Toughness>5</Toughness>
<Offhand_Attack>0</Offhand_Attack>
<Move_Ap_Penalty>0</Move_Ap_Penalty>
<Block_Chance>0</Block_Chance>
<Spellpower>4</Spellpower>
<Attack_Bonus>0</Attack_Bonus>
<Concealment>0</Concealment>
<Axe_Mastery>0</Axe_Mastery>
<Default_Spellpower>4</Default_Spellpower>
<Initiative_Bonus>5</Initiative_Bonus>
<Blunt_Mastery>0</Blunt_Mastery>
<Vitality>7</Vitality>
<Psionic_Resistance>0</Psionic_Resistance>
<Power>7</Power>
<Elemental_Mastery>0</Elemental_Mastery>
<Base_Agility>5</Base_Agility>
<Polearm_Mastery>0</Polearm_Mastery>
<Intelligence>5</Intelligence>
<Starting_Focus>25</Starting_Focus>
<Piercing_Resistance>0</Piercing_Resistance>
<Spell_Armor>0</Spell_Armor>
<Magic_Affinity>50</Magic_Affinity>
<Toughness_Percentage>100</Toughness_Percentage>
<Gold_Cost_Reduction>0</Gold_Cost_Reduction>
<Two_Handed_Mastery>0</Two_Handed_Mastery>
<Air_Resistance>0</Air_Resistance>
<Focus_Percentage>100</Focus_Percentage>
<Spellcraft_Mastery>0</Spellcraft_Mastery>
<Detection>0</Detection>
<C_N_Of_Moves>2</C_N_Of_Moves>
<Default_Willpower>8</Default_Willpower>
<Base_Vitality>7</Base_Vitality>
<Divination_Mastery>0</Divination_Mastery>
<Base_Damage>10</Base_Damage>
<Default_Wisdom>5</Default_Wisdom>
<Base_Dexterity>5</Base_Dexterity>
<Resistance>15</Resistance>
<Claimed_Gateways>0</Claimed_Gateways>
<Attack>5</Attack>
<Weight>140</Weight>
<Death_Resistance>0</Death_Resistance>
<Base_Wisdom>5</Base_Wisdom>
<Essence>25</Essence>
<Strength>9</Strength>
<Conjuration_Mastery>0</Conjuration_Mastery>
<Attack_Ap_Penalty>0</Attack_Ap_Penalty>
<Default_Strength>9</Default_Strength>
<Off_Hand_Min_Damage>0</Off_Hand_Min_Damage>
<N_Of_Counters>1</N_Of_Counters>
<Defense_Penetration>0</Defense_Penetration>
<Quick_Slots>4</Quick_Slots>
<Default_Vitality>7</Default_Vitality>
<Actions_Remaining>0</Actions_Remaining>
<Off_Hand_Damage>0</Off_Hand_Damage>
<N_Of_Counters_Percentage>1000000</N_Of_Counters_Percentage>
<Default_Charisma>6</Default_Charisma>
<Willpower>8</Willpower>
<Stealth>0</Stealth>
<Essence_Regen>0</Essence_Regen>
<Max_Damage>0</Max_Damage>
<Level>3</Level>
<Gold_Cost>50</Gold_Cost>
<Interrupt_Damage>100</Interrupt_Damage>
<Destruction_Mastery>0</Destruction_Mastery>
<Defense_Mod>100</Defense_Mod>
<Xp_Cost>0</Xp_Cost>
<Offhand_Attack_Ap_Penalty>0</Offhand_Attack_Ap_Penalty>
<Claimed_Crystals>0</Claimed_Crystals>
<Xp_Cost_Reduction_Learned_Spells>0</Xp_Cost_Reduction_Learned_Spells>
<C_Carrying_Weight>0</C_Carrying_Weight>
<Mastery_Points_Per_Level>11</Mastery_Points_Per_Level>
<Water_Resistance>0</Water_Resistance>
<Damage_Mod>100</Damage_Mod>
<Total_Xp>519</Total_Xp>
<Counter_Mod>50</Counter_Mod>
<Base_Charisma>6</Base_Charisma>
<Sylvan_Mastery>0</Sylvan_Mastery>
<Endurance_Percentage>100</Endurance_Percentage>
<C_Initiative>0</C_Initiative>
<Xp_Cost_Reduction>0</Xp_Cost_Reduction>
<Holy_Resistance>0</Holy_Resistance>
<Fire_Resistance>0</Fire_Resistance>
<Base_Spellpower>4</Base_Spellpower>
<Divination_Cap>0</Divination_Cap>
<Dexterity>30</Dexterity>
<Ap_Penalty>0</Ap_Penalty>
<Default_Knowledge>5</Default_Knowledge>
<Unarmed_Combat_Mastery>0</Unarmed_Combat_Mastery>
<Poison_Resistance>0</Poison_Resistance>
<Offhand_Attack_Sta_Penalty>0</Offhand_Attack_Sta_Penalty>
<Blade_Mastery>10</Blade_Mastery>
<Hero_Level>3</Hero_Level>
<Xp_Cost_Reduction_Skills>0</Xp_Cost_Reduction_Skills>
<Turns_In_Game>0</Turns_In_Game>
<Spell_Sta_Penalty>0</Spell_Sta_Penalty>
<N_Of_Actions>4</N_Of_Actions>
<Attr_Points_Per_Level>8</Attr_Points_Per_Level>
<Sorcery_Mastery>0</Sorcery_Mastery>
<Dual_Wielding_Mastery>0</Dual_Wielding_Mastery>
<Default_Dexterity>5</Default_Dexterity>
<Default_Intelligence>5</Default_Intelligence>
<Armor_Penetration>0</Armor_Penetration>
<Knowledge>5</Knowledge>
<Free_Masteries>3</Free_Masteries>
<Attack_Sta_Penalty>0</Attack_Sta_Penalty>
<Offhand_Attack_Mod>50</Offhand_Attack_Mod>
<Earth_Resistance>0</Earth_Resistance>
<Base_Willpower>8</Base_Willpower>
<Resistance_Penetration>0</Resistance_Penetration>
<Armorer_Mastery>6</Armorer_Mastery>
<Sight_Range>3</Sight_Range>
<Concentration_Bonus>0</Concentration_Bonus>
<Shield_Mastery>0</Shield_Mastery>
<Move_Sta_Penalty>0</Move_Sta_Penalty>
<Armor_Mod>100</Armor_Mod>
<Witchery_Mastery>0</Witchery_Mastery>
<Initiative>0</Initiative>
<Base_Intelligence>5</Base_Intelligence>
<Memorization_Cap>4</Memorization_Cap>
<Gold>135</Gold>
<N_Of_Actions_Percentage>1000000</N_Of_Actions_Percentage>
<Defense>5</Defense>
<Off_Hand_Max_Damage>0</Off_Hand_Max_Damage>
<Defense_Mastery>0</Defense_Mastery>
<Focus_Regen>0</Focus_Regen>
<Xp_Cost_Reduction_Masteries>0</Xp_Cost_Reduction_Masteries>
<Stamina_Penalty>0</Stamina_Penalty>
<Base_Knowledge>5</Base_Knowledge>
<Morale>30</Morale>
<Damage>0</Damage>
<Endurance>30</Endurance>
<Essence_Percentage>100</Essence_Percentage>
<Offhand_Damage_Mod>75</Offhand_Damage_Mod>
<Memory_Remaining>4</Memory_Remaining>
<Meditation_Mastery>0</Meditation_Mastery>
<Celestial_Mastery>0</Celestial_Mastery>
<Demonology_Mastery>0</Demonology_Mastery>
<Stamina_Regen>0</Stamina_Regen>
<Benediction_Mastery>0</Benediction_Mastery>
<Discipline_Mastery>3</Discipline_Mastery>
<Detection_Mastery>0</Detection_Mastery>
<Mastery_Points>24</Mastery_Points>
<Wisdom>5</Wisdom>
<Shadow_Mastery>0</Shadow_Mastery>
<Attr_Points>18</Attr_Points>
<Spell_Ess_Penalty>0</Spell_Ess_Penalty>
<Affliction_Mastery>0</Affliction_Mastery>
<Spirit>4</Spirit>
<Charisma>31</Charisma>
<Min_Damage>0</Min_Damage>
<Stealth_Mastery>0</Stealth_Mastery>
<Xp_Level_Mod>100</Xp_Level_Mod>
<Focus>100</Focus>
</params><props><Custom_Params></Custom_Params>
<Classifications></Classifications>
<Group>Preset</Group>
<Verbatim_Spells></Verbatim_Spells>
<Off_Hand_Item></Off_Hand_Item>
<Learned_Spells></Learned_Spells>
<Custom_Props></Custom_Props>
<Memorized_Spells></Memorized_Spells>
<Counter_Attack_Action></Counter_Attack_Action>
<Emblem></Emblem>
<Principles>Honor;Law;Ambition;</Principles>
<Special_Abilities></Special_Abilities>
<First_Class></First_Class>
<Background>Man Of Kings Realm</Background>
<Status></Status>
<Custom_Soundset></Custom_Soundset>
<Visibility_Status></Visibility_Status>
<Name>Sir Richard</Name>
<Inventory>Legendary Pendant of Base Charisma;Ancient Iron Long Sword;</Inventory>
<Gender></Gender>
<Divined_Spells></Divined_Spells>
<On_Being_Hit></On_Being_Hit>
<Description></Description>
<Base_Type></Base_Type>
<Deity>Allfather</Deity>
<Spellbook></Spellbook>
<On_Hit></On_Hit>
<Classes></Classes>
<Prepared_Spells></Prepared_Spells>
<Lore></Lore>
<Party_Units></Party_Units>
<Main_Hand_Item>Damaged Palewood Short Bow</Main_Hand_Item>
<Vision_Mode></Vision_Mode>
<Second_Class></Second_Class>
<Type>chars</Type>
<Skills></Skills>
<Standard_Passives></Standard_Passives>
<Actives></Actives>
<Mode></Mode>
<Hired_Mercenaries></Hired_Mercenaries>
<Soundset></Soundset>
<Std_Bools></Std_Bools>
<On_Kill></On_Kill>
<Facing_Direction></Facing_Direction>
<Race>Human</Race>
<Rank>New Hero</Rank>
<Aspect>Neutral</Aspect>
<Jewelry>Golden Ring;Legendary Pendant of Base Charisma;Legendary Golden Ring of Base Dexterity;</Jewelry>
<Known_Spells></Known_Spells>
<Attack_Of_Opportunity_Action></Attack_Of_Opportunity_Action>
<Passives></Passives>
<Armor_Item>Ancient Iron Half Plate</Armor_Item>
<Xp_Plan></Xp_Plan>
<Detection_Status></Detection_Status>
<Quick_Items>Damaged Copper Arrows;Damaged Copper Knife;Ancient Copper Short Sword;Kris;</Quick_Items>
<Image>mini\char\std\human\King Realm\knight.jpg</Image>
<Variables></Variables>
</props></Sir_Richard></Party>